<?xml version="1.0" ?>
<scenario>
  <obstacle x1="-5.91" y1="5.189999999999999" x2="-5.970000000000001" y2="5.249999999999999"/>
  <obstacle x1="-5.85" y1="5.189999999999999" x2="-5.91" y2="5.249999999999999"/>
  <obstacle x1="-5.79" y1="5.189999999999999" x2="-5.8500000000000005" y2="5.249999999999999"/>
  <obstacle x1="-5.7299999999999995" y1="5.189999999999999" x2="-5.79" y2="5.249999999999999"/>
  <obstacle x1="-5.67" y1="5.189999999999999" x2="-5.73" y2="5.249999999999999"/>
  <obstacle x1="-5.609999999999999" y1="5.189999999999999" x2="-5.67" y2="5.249999999999999"/>
  <obstacle x1="-5.55" y1="5.189999999999999" x2="-5.61" y2="5.249999999999999"/>
  <obstacle x1="-5.489999999999999" y1="5.189999999999999" x2="-5.55" y2="5.249999999999999"/>
  <obstacle x1="-5.43" y1="5.189999999999999" x2="-5.49" y2="5.249999999999999"/>
  <obstacle x1="-5.37" y1="5.189999999999999" x2="-5.430000000000001" y2="5.249999999999999"/>
  <obstacle x1="-5.31" y1="5.189999999999999" x2="-5.37" y2="5.249999999999999"/>
  <obstacle x1="-5.25" y1="5.189999999999999" x2="-5.3100000000000005" y2="5.249999999999999"/>
  <obstacle x1="-5.1899999999999995" y1="5.189999999999999" x2="-5.25" y2="5.249999999999999"/>
  <obstacle x1="-5.13" y1="5.189999999999999" x2="-5.19" y2="5.249999999999999"/>
  <obstacle x1="-5.069999999999999" y1="5.189999999999999" x2="-5.13" y2="5.249999999999999"/>
  <obstacle x1="-5.01" y1="5.189999999999999" x2="-5.07" y2="5.249999999999999"/>
  <obstacle x1="-4.95" y1="5.189999999999999" x2="-5.010000000000001" y2="5.249999999999999"/>
  <obstacle x1="-4.89" y1="5.189999999999999" x2="-4.95" y2="5.249999999999999"/>
  <obstacle x1="-4.83" y1="5.189999999999999" x2="-4.890000000000001" y2="5.249999999999999"/>
  <obstacle x1="-4.77" y1="5.189999999999999" x2="-4.83" y2="5.249999999999999"/>
  <obstacle x1="-4.71" y1="5.189999999999999" x2="-4.7700000000000005" y2="5.249999999999999"/>
  <obstacle x1="-4.6499999999999995" y1="5.189999999999999" x2="-4.71" y2="5.249999999999999"/>
  <obstacle x1="-4.59" y1="5.189999999999999" x2="-4.65" y2="5.249999999999999"/>
  <obstacle x1="-4.53" y1="5.189999999999999" x2="-4.590000000000001" y2="5.249999999999999"/>
  <obstacle x1="-4.47" y1="5.189999999999999" x2="-4.53" y2="5.249999999999999"/>
  <obstacle x1="-4.409999999999999" y1="5.189999999999999" x2="-4.47" y2="5.249999999999999"/>
  <obstacle x1="-4.35" y1="5.189999999999999" x2="-4.41" y2="5.249999999999999"/>
  <obstacle x1="-4.29" y1="5.189999999999999" x2="-4.3500000000000005" y2="5.249999999999999"/>
  <obstacle x1="-4.2299999999999995" y1="5.189999999999999" x2="-4.29" y2="5.249999999999999"/>
  <obstacle x1="-4.17" y1="5.189999999999999" x2="-4.23" y2="5.249999999999999"/>
  <obstacle x1="-4.11" y1="5.189999999999999" x2="-4.170000000000001" y2="5.249999999999999"/>
  <obstacle x1="-4.05" y1="5.189999999999999" x2="-4.11" y2="5.249999999999999"/>
  <obstacle x1="-3.9899999999999998" y1="5.189999999999999" x2="-4.05" y2="5.249999999999999"/>
  <obstacle x1="-3.93" y1="5.189999999999999" x2="-3.9899999999999998" y2="5.249999999999999"/>
  <obstacle x1="-3.87" y1="5.189999999999999" x2="-3.9299999999999997" y2="5.249999999999999"/>
  <obstacle x1="-3.81" y1="5.189999999999999" x2="-3.8699999999999997" y2="5.249999999999999"/>
  <obstacle x1="-3.7500000000000004" y1="5.189999999999999" x2="-3.81" y2="5.249999999999999"/>
  <obstacle x1="-3.6900000000000004" y1="5.189999999999999" x2="-3.75" y2="5.249999999999999"/>
  <obstacle x1="-3.6300000000000003" y1="5.189999999999999" x2="-3.69" y2="5.249999999999999"/>
  <obstacle x1="-3.5700000000000003" y1="5.189999999999999" x2="-3.63" y2="5.249999999999999"/>
  <obstacle x1="-3.5100000000000002" y1="5.189999999999999" x2="-3.57" y2="5.249999999999999"/>
  <obstacle x1="-3.45" y1="5.189999999999999" x2="-3.51" y2="5.249999999999999"/>
  <obstacle x1="-3.39" y1="5.189999999999999" x2="-3.4499999999999997" y2="5.249999999999999"/>
  <obstacle x1="-3.3300000000000005" y1="5.189999999999999" x2="-3.39" y2="5.249999999999999"/>
  <obstacle x1="-3.2700000000000005" y1="5.189999999999999" x2="-3.33" y2="5.249999999999999"/>
  <obstacle x1="-3.2100000000000004" y1="5.189999999999999" x2="-3.27" y2="5.249999999999999"/>
  <obstacle x1="-3.1500000000000004" y1="5.189999999999999" x2="-3.21" y2="5.249999999999999"/>
  <obstacle x1="-3.0900000000000003" y1="5.189999999999999" x2="-3.15" y2="5.249999999999999"/>
  <obstacle x1="-3.0300000000000002" y1="5.189999999999999" x2="-3.09" y2="5.249999999999999"/>
  <obstacle x1="-2.97" y1="5.189999999999999" x2="-3.03" y2="5.249999999999999"/>
  <obstacle x1="-2.91" y1="5.189999999999999" x2="-2.9699999999999998" y2="5.249999999999999"/>
  <obstacle x1="-2.85" y1="5.189999999999999" x2="-2.9099999999999997" y2="5.249999999999999"/>
  <obstacle x1="-2.7900000000000005" y1="5.189999999999999" x2="-2.85" y2="5.249999999999999"/>
  <obstacle x1="-2.7300000000000004" y1="5.189999999999999" x2="-2.79" y2="5.249999999999999"/>
  <obstacle x1="-2.6700000000000004" y1="5.189999999999999" x2="-2.73" y2="5.249999999999999"/>
  <obstacle x1="-2.6100000000000003" y1="5.189999999999999" x2="-2.67" y2="5.249999999999999"/>
  <obstacle x1="-2.5500000000000003" y1="5.189999999999999" x2="-2.61" y2="5.249999999999999"/>
  <obstacle x1="-2.49" y1="5.189999999999999" x2="-2.55" y2="5.249999999999999"/>
  <obstacle x1="-2.43" y1="5.189999999999999" x2="-2.4899999999999998" y2="5.249999999999999"/>
  <obstacle x1="-2.3700000000000006" y1="5.189999999999999" x2="-2.43" y2="5.249999999999999"/>
  <obstacle x1="-2.3100000000000005" y1="5.189999999999999" x2="-2.37" y2="5.249999999999999"/>
  <obstacle x1="-2.2500000000000004" y1="5.189999999999999" x2="-2.31" y2="5.249999999999999"/>
  <obstacle x1="-2.1900000000000004" y1="5.189999999999999" x2="-2.25" y2="5.249999999999999"/>
  <obstacle x1="-2.1300000000000003" y1="5.189999999999999" x2="-2.19" y2="5.249999999999999"/>
  <obstacle x1="-2.0700000000000003" y1="5.189999999999999" x2="-2.13" y2="5.249999999999999"/>
  <obstacle x1="-2.0100000000000002" y1="5.189999999999999" x2="-2.07" y2="5.249999999999999"/>
  <obstacle x1="-1.9500000000000004" y1="5.189999999999999" x2="-2.0100000000000002" y2="5.249999999999999"/>
  <obstacle x1="-1.89" y1="5.189999999999999" x2="-1.95" y2="5.249999999999999"/>
  <obstacle x1="-1.8300000000000003" y1="5.189999999999999" x2="-1.8900000000000003" y2="5.249999999999999"/>
  <obstacle x1="-1.7699999999999998" y1="5.189999999999999" x2="-1.8299999999999998" y2="5.249999999999999"/>
  <obstacle x1="-1.7100000000000002" y1="5.189999999999999" x2="-1.7700000000000002" y2="5.249999999999999"/>
  <obstacle x1="-1.6499999999999997" y1="5.189999999999999" x2="-1.7099999999999997" y2="5.249999999999999"/>
  <obstacle x1="-1.59" y1="5.189999999999999" x2="-1.6500000000000001" y2="5.249999999999999"/>
  <obstacle x1="-1.5300000000000005" y1="5.189999999999999" x2="-1.5900000000000005" y2="5.249999999999999"/>
  <obstacle x1="-1.47" y1="5.189999999999999" x2="-1.53" y2="5.249999999999999"/>
  <obstacle x1="-1.4100000000000004" y1="5.189999999999999" x2="-1.4700000000000004" y2="5.249999999999999"/>
  <obstacle x1="-1.3499999999999999" y1="5.189999999999999" x2="-1.41" y2="5.249999999999999"/>
  <obstacle x1="-1.2900000000000003" y1="5.189999999999999" x2="-1.3500000000000003" y2="5.249999999999999"/>
  <obstacle x1="-1.2299999999999998" y1="5.189999999999999" x2="-1.2899999999999998" y2="5.249999999999999"/>
  <obstacle x1="-1.1700000000000002" y1="5.189999999999999" x2="-1.2300000000000002" y2="5.249999999999999"/>
  <obstacle x1="-1.1100000000000005" y1="5.189999999999999" x2="-1.1700000000000006" y2="5.249999999999999"/>
  <obstacle x1="-1.05" y1="5.189999999999999" x2="-1.11" y2="5.249999999999999"/>
  <obstacle x1="-0.9900000000000004" y1="5.189999999999999" x2="-1.0500000000000005" y2="5.249999999999999"/>
  <obstacle x1="-0.9299999999999999" y1="5.189999999999999" x2="-0.99" y2="5.249999999999999"/>
  <obstacle x1="-0.8700000000000003" y1="5.189999999999999" x2="-0.9300000000000004" y2="5.249999999999999"/>
  <obstacle x1="-0.8099999999999998" y1="5.189999999999999" x2="-0.8699999999999999" y2="5.249999999999999"/>
  <obstacle x1="-0.7500000000000002" y1="5.189999999999999" x2="-0.8100000000000003" y2="5.249999999999999"/>
  <obstacle x1="-0.6900000000000006" y1="5.189999999999999" x2="-0.7500000000000007" y2="5.249999999999999"/>
  <obstacle x1="-0.6300000000000001" y1="5.189999999999999" x2="-0.6900000000000002" y2="5.249999999999999"/>
  <obstacle x1="-0.5700000000000005" y1="5.189999999999999" x2="-0.6300000000000006" y2="5.249999999999999"/>
  <obstacle x1="-0.51" y1="5.189999999999999" x2="-0.5700000000000001" y2="5.249999999999999"/>
  <obstacle x1="-0.4500000000000004" y1="5.189999999999999" x2="-0.5100000000000005" y2="5.249999999999999"/>
  <obstacle x1="-0.3899999999999999" y1="5.189999999999999" x2="-0.44999999999999996" y2="5.249999999999999"/>
  <obstacle x1="-0.3300000000000003" y1="5.189999999999999" x2="-0.39000000000000035" y2="5.249999999999999"/>
  <obstacle x1="-0.2699999999999998" y1="5.189999999999999" x2="-0.32999999999999985" y2="5.249999999999999"/>
  <obstacle x1="-0.21000000000000021" y1="5.189999999999999" x2="-0.27000000000000024" y2="5.249999999999999"/>
  <obstacle x1="-0.1500000000000006" y1="5.189999999999999" x2="-0.2100000000000006" y2="5.249999999999999"/>
  <obstacle x1="-0.09000000000000011" y1="5.189999999999999" x2="-0.1500000000000001" y2="5.249999999999999"/>
  <obstacle x1="-0.0300000000000005" y1="5.189999999999999" x2="-0.0900000000000005" y2="5.249999999999999"/>
  <obstacle x1="0.03" y1="5.189999999999999" x2="-0.03" y2="5.249999999999999"/>
  <obstacle x1="0.08999999999999961" y1="5.189999999999999" x2="0.02999999999999961" y2="5.249999999999999"/>
  <obstacle x1="0.1500000000000001" y1="5.189999999999999" x2="0.09000000000000011" y2="5.249999999999999"/>
  <obstacle x1="0.20999999999999971" y1="5.189999999999999" x2="0.14999999999999972" y2="5.249999999999999"/>
  <obstacle x1="0.27000000000000024" y1="5.189999999999999" x2="0.21000000000000021" y2="5.249999999999999"/>
  <obstacle x1="0.32999999999999985" y1="5.189999999999999" x2="0.2699999999999998" y2="5.249999999999999"/>
  <obstacle x1="0.38999999999999946" y1="5.189999999999999" x2="0.3299999999999994" y2="5.249999999999999"/>
  <obstacle x1="0.44999999999999996" y1="5.189999999999999" x2="0.3899999999999999" y2="5.249999999999999"/>
  <obstacle x1="0.5099999999999996" y1="5.189999999999999" x2="0.4499999999999995" y2="5.249999999999999"/>
  <obstacle x1="0.5700000000000001" y1="5.189999999999999" x2="0.51" y2="5.249999999999999"/>
  <obstacle x1="0.6299999999999997" y1="5.189999999999999" x2="0.5699999999999996" y2="5.249999999999999"/>
  <obstacle x1="0.6900000000000002" y1="5.189999999999999" x2="0.6300000000000001" y2="5.249999999999999"/>
  <obstacle x1="0.7499999999999998" y1="5.189999999999999" x2="0.6899999999999997" y2="5.249999999999999"/>
  <obstacle x1="0.8099999999999994" y1="5.189999999999999" x2="0.7499999999999993" y2="5.249999999999999"/>
  <obstacle x1="0.8699999999999999" y1="5.189999999999999" x2="0.8099999999999998" y2="5.249999999999999"/>
  <obstacle x1="0.9299999999999995" y1="5.189999999999999" x2="0.8699999999999994" y2="5.249999999999999"/>
  <obstacle x1="0.99" y1="5.189999999999999" x2="0.9299999999999999" y2="5.249999999999999"/>
  <obstacle x1="1.0499999999999996" y1="5.189999999999999" x2="0.9899999999999995" y2="5.249999999999999"/>
  <obstacle x1="1.11" y1="5.189999999999999" x2="1.05" y2="5.249999999999999"/>
  <obstacle x1="1.1699999999999997" y1="5.189999999999999" x2="1.1099999999999997" y2="5.249999999999999"/>
  <obstacle x1="1.2299999999999993" y1="5.189999999999999" x2="1.1699999999999993" y2="5.249999999999999"/>
  <obstacle x1="1.2899999999999998" y1="5.189999999999999" x2="1.2299999999999998" y2="5.249999999999999"/>
  <obstacle x1="1.3499999999999994" y1="5.189999999999999" x2="1.2899999999999994" y2="5.249999999999999"/>
  <obstacle x1="1.41" y1="5.189999999999999" x2="1.3499999999999999" y2="5.249999999999999"/>
  <obstacle x1="1.4699999999999995" y1="5.189999999999999" x2="1.4099999999999995" y2="5.249999999999999"/>
  <obstacle x1="1.53" y1="5.189999999999999" x2="1.47" y2="5.249999999999999"/>
  <obstacle x1="1.5899999999999996" y1="5.189999999999999" x2="1.5299999999999996" y2="5.249999999999999"/>
  <obstacle x1="1.6500000000000001" y1="5.189999999999999" x2="1.59" y2="5.249999999999999"/>
  <obstacle x1="1.7099999999999997" y1="5.189999999999999" x2="1.6499999999999997" y2="5.249999999999999"/>
  <obstacle x1="1.7699999999999994" y1="5.189999999999999" x2="1.7099999999999993" y2="5.249999999999999"/>
  <obstacle x1="1.8299999999999998" y1="5.189999999999999" x2="1.7699999999999998" y2="5.249999999999999"/>
  <obstacle x1="1.8899999999999995" y1="5.189999999999999" x2="1.8299999999999994" y2="5.249999999999999"/>
  <obstacle x1="1.95" y1="5.189999999999999" x2="1.89" y2="5.249999999999999"/>
  <obstacle x1="2.0099999999999993" y1="5.189999999999999" x2="1.9499999999999995" y2="5.249999999999999"/>
  <obstacle x1="2.069999999999999" y1="5.189999999999999" x2="2.0099999999999993" y2="5.249999999999999"/>
  <obstacle x1="2.1299999999999994" y1="5.189999999999999" x2="2.07" y2="5.249999999999999"/>
  <obstacle x1="2.19" y1="5.189999999999999" x2="2.1300000000000003" y2="5.249999999999999"/>
  <obstacle x1="2.2499999999999987" y1="5.189999999999999" x2="2.189999999999999" y2="5.249999999999999"/>
  <obstacle x1="2.309999999999999" y1="5.189999999999999" x2="2.2499999999999996" y2="5.249999999999999"/>
  <obstacle x1="2.3699999999999997" y1="5.189999999999999" x2="2.31" y2="5.249999999999999"/>
  <obstacle x1="2.43" y1="5.189999999999999" x2="2.3700000000000006" y2="5.249999999999999"/>
  <obstacle x1="2.489999999999999" y1="5.189999999999999" x2="2.4299999999999993" y2="5.249999999999999"/>
  <obstacle x1="2.5499999999999994" y1="5.189999999999999" x2="2.4899999999999998" y2="5.249999999999999"/>
  <obstacle x1="2.61" y1="5.189999999999999" x2="2.5500000000000003" y2="5.249999999999999"/>
  <obstacle x1="2.6700000000000004" y1="5.189999999999999" x2="2.6100000000000008" y2="5.249999999999999"/>
  <obstacle x1="2.729999999999999" y1="5.189999999999999" x2="2.6699999999999995" y2="5.249999999999999"/>
  <obstacle x1="2.7899999999999996" y1="5.189999999999999" x2="2.73" y2="5.249999999999999"/>
  <obstacle x1="2.85" y1="5.189999999999999" x2="2.7900000000000005" y2="5.249999999999999"/>
  <obstacle x1="2.909999999999999" y1="5.189999999999999" x2="2.849999999999999" y2="5.249999999999999"/>
  <obstacle x1="2.9699999999999993" y1="5.189999999999999" x2="2.9099999999999997" y2="5.249999999999999"/>
  <obstacle x1="3.03" y1="5.189999999999999" x2="2.97" y2="5.249999999999999"/>
  <obstacle x1="3.0900000000000003" y1="5.189999999999999" x2="3.0300000000000007" y2="5.249999999999999"/>
  <obstacle x1="3.149999999999999" y1="5.189999999999999" x2="3.0899999999999994" y2="5.249999999999999"/>
  <obstacle x1="3.2099999999999995" y1="5.189999999999999" x2="3.15" y2="5.249999999999999"/>
  <obstacle x1="3.27" y1="5.189999999999999" x2="3.2100000000000004" y2="5.249999999999999"/>
  <obstacle x1="3.3299999999999987" y1="5.189999999999999" x2="3.269999999999999" y2="5.249999999999999"/>
  <obstacle x1="3.3899999999999992" y1="5.189999999999999" x2="3.3299999999999996" y2="5.249999999999999"/>
  <obstacle x1="3.4499999999999997" y1="5.189999999999999" x2="3.39" y2="5.249999999999999"/>
  <obstacle x1="3.5100000000000002" y1="5.189999999999999" x2="3.4500000000000006" y2="5.249999999999999"/>
  <obstacle x1="3.569999999999999" y1="5.189999999999999" x2="3.5099999999999993" y2="5.249999999999999"/>
  <obstacle x1="3.6299999999999994" y1="5.189999999999999" x2="3.57" y2="5.249999999999999"/>
  <obstacle x1="3.69" y1="5.189999999999999" x2="3.6300000000000003" y2="5.249999999999999"/>
  <obstacle x1="3.7499999999999987" y1="5.189999999999999" x2="3.689999999999999" y2="5.249999999999999"/>
  <obstacle x1="3.809999999999999" y1="5.189999999999999" x2="3.7499999999999996" y2="5.249999999999999"/>
  <obstacle x1="3.8699999999999997" y1="5.189999999999999" x2="3.81" y2="5.249999999999999"/>
  <obstacle x1="3.93" y1="5.189999999999999" x2="3.8700000000000006" y2="5.249999999999999"/>
  <obstacle x1="3.989999999999999" y1="5.189999999999999" x2="3.9299999999999993" y2="5.249999999999999"/>
  <obstacle x1="4.05" y1="5.189999999999999" x2="3.9899999999999998" y2="5.249999999999999"/>
  <obstacle x1="4.11" y1="5.189999999999999" x2="4.05" y2="5.249999999999999"/>
  <obstacle x1="4.169999999999999" y1="5.189999999999999" x2="4.1099999999999985" y2="5.249999999999999"/>
  <obstacle x1="4.2299999999999995" y1="5.189999999999999" x2="4.169999999999999" y2="5.249999999999999"/>
  <obstacle x1="4.29" y1="5.189999999999999" x2="4.2299999999999995" y2="5.249999999999999"/>
  <obstacle x1="4.3500000000000005" y1="5.189999999999999" x2="4.29" y2="5.249999999999999"/>
  <obstacle x1="4.409999999999999" y1="5.189999999999999" x2="4.349999999999999" y2="5.249999999999999"/>
  <obstacle x1="4.47" y1="5.189999999999999" x2="4.409999999999999" y2="5.249999999999999"/>
  <obstacle x1="4.53" y1="5.189999999999999" x2="4.47" y2="5.249999999999999"/>
  <obstacle x1="4.589999999999999" y1="5.189999999999999" x2="4.5299999999999985" y2="5.249999999999999"/>
  <obstacle x1="4.6499999999999995" y1="5.189999999999999" x2="4.589999999999999" y2="5.249999999999999"/>
  <obstacle x1="4.71" y1="5.189999999999999" x2="4.6499999999999995" y2="5.249999999999999"/>
  <obstacle x1="4.7700000000000005" y1="5.189999999999999" x2="4.71" y2="5.249999999999999"/>
  <obstacle x1="4.829999999999999" y1="5.189999999999999" x2="4.769999999999999" y2="5.249999999999999"/>
  <obstacle x1="4.89" y1="5.189999999999999" x2="4.829999999999999" y2="5.249999999999999"/>
  <obstacle x1="4.95" y1="5.189999999999999" x2="4.89" y2="5.249999999999999"/>
  <obstacle x1="5.010000000000001" y1="5.189999999999999" x2="4.95" y2="5.249999999999999"/>
  <obstacle x1="5.069999999999999" y1="5.189999999999999" x2="5.009999999999999" y2="5.249999999999999"/>
  <obstacle x1="5.13" y1="5.189999999999999" x2="5.069999999999999" y2="5.249999999999999"/>
  <obstacle x1="5.19" y1="5.189999999999999" x2="5.13" y2="5.249999999999999"/>
  <obstacle x1="5.249999999999999" y1="5.189999999999999" x2="5.189999999999999" y2="5.249999999999999"/>
  <obstacle x1="5.31" y1="5.189999999999999" x2="5.249999999999999" y2="5.249999999999999"/>
  <obstacle x1="5.37" y1="5.189999999999999" x2="5.31" y2="5.249999999999999"/>
  <obstacle x1="5.430000000000001" y1="5.189999999999999" x2="5.37" y2="5.249999999999999"/>
  <obstacle x1="5.489999999999999" y1="5.189999999999999" x2="5.429999999999999" y2="5.249999999999999"/>
  <obstacle x1="5.55" y1="5.189999999999999" x2="5.489999999999999" y2="5.249999999999999"/>
  <obstacle x1="5.61" y1="5.189999999999999" x2="5.55" y2="5.249999999999999"/>
  <obstacle x1="5.669999999999999" y1="5.189999999999999" x2="5.6099999999999985" y2="5.249999999999999"/>
  <obstacle x1="5.7299999999999995" y1="5.189999999999999" x2="5.669999999999999" y2="5.249999999999999"/>
  <obstacle x1="5.79" y1="5.189999999999999" x2="5.7299999999999995" y2="5.249999999999999"/>
  <obstacle x1="5.8500000000000005" y1="5.189999999999999" x2="5.79" y2="5.249999999999999"/>
  <obstacle x1="5.909999999999999" y1="5.189999999999999" x2="5.849999999999999" y2="5.249999999999999"/>
  <obstacle x1="5.97" y1="5.189999999999999" x2="5.909999999999999" y2="5.249999999999999"/>
  <obstacle x1="6.03" y1="5.189999999999999" x2="5.97" y2="5.249999999999999"/>
  <obstacle x1="6.089999999999999" y1="5.189999999999999" x2="6.0299999999999985" y2="5.249999999999999"/>
  <obstacle x1="6.1499999999999995" y1="5.189999999999999" x2="6.089999999999999" y2="5.249999999999999"/>
  <obstacle x1="6.21" y1="5.189999999999999" x2="6.1499999999999995" y2="5.249999999999999"/>
  <obstacle x1="6.2700000000000005" y1="5.189999999999999" x2="6.21" y2="5.249999999999999"/>
  <obstacle x1="6.329999999999999" y1="5.189999999999999" x2="6.269999999999999" y2="5.249999999999999"/>
  <obstacle x1="6.39" y1="5.189999999999999" x2="6.329999999999999" y2="5.249999999999999"/>
  <obstacle x1="6.45" y1="5.189999999999999" x2="6.39" y2="5.249999999999999"/>
  <obstacle x1="6.510000000000001" y1="5.189999999999999" x2="6.45" y2="5.249999999999999"/>
  <obstacle x1="6.569999999999999" y1="5.189999999999999" x2="6.509999999999999" y2="5.249999999999999"/>
  <obstacle x1="6.63" y1="5.189999999999999" x2="6.569999999999999" y2="5.249999999999999"/>
  <obstacle x1="6.69" y1="5.189999999999999" x2="6.63" y2="5.249999999999999"/>
  <obstacle x1="6.749999999999999" y1="5.189999999999999" x2="6.689999999999999" y2="5.249999999999999"/>
  <obstacle x1="6.81" y1="5.189999999999999" x2="6.749999999999999" y2="5.249999999999999"/>
  <obstacle x1="6.87" y1="5.189999999999999" x2="6.81" y2="5.249999999999999"/>
  <obstacle x1="6.930000000000001" y1="5.189999999999999" x2="6.87" y2="5.249999999999999"/>
  <obstacle x1="6.989999999999999" y1="5.189999999999999" x2="6.929999999999999" y2="5.249999999999999"/>
  <obstacle x1="7.05" y1="5.189999999999999" x2="6.989999999999999" y2="5.249999999999999"/>
  <obstacle x1="7.11" y1="5.189999999999999" x2="7.05" y2="5.249999999999999"/>
  <obstacle x1="7.169999999999999" y1="5.189999999999999" x2="7.1099999999999985" y2="5.249999999999999"/>
  <obstacle x1="7.2299999999999995" y1="5.189999999999999" x2="7.169999999999999" y2="5.249999999999999"/>
  <obstacle x1="7.29" y1="5.189999999999999" x2="7.2299999999999995" y2="5.249999999999999"/>
  <obstacle x1="7.3500000000000005" y1="5.189999999999999" x2="7.29" y2="5.249999999999999"/>
  <obstacle x1="7.409999999999999" y1="5.189999999999999" x2="7.349999999999999" y2="5.249999999999999"/>
  <obstacle x1="7.47" y1="5.189999999999999" x2="7.409999999999999" y2="5.249999999999999"/>
  <obstacle x1="7.53" y1="5.189999999999999" x2="7.47" y2="5.249999999999999"/>
  <obstacle x1="7.589999999999999" y1="5.189999999999999" x2="7.5299999999999985" y2="5.249999999999999"/>
  <obstacle x1="7.6499999999999995" y1="5.189999999999999" x2="7.589999999999999" y2="5.249999999999999"/>
  <obstacle x1="7.71" y1="5.189999999999999" x2="7.6499999999999995" y2="5.249999999999999"/>
  <obstacle x1="7.7700000000000005" y1="5.189999999999999" x2="7.71" y2="5.249999999999999"/>
  <obstacle x1="7.829999999999999" y1="5.189999999999999" x2="7.769999999999999" y2="5.249999999999999"/>
  <obstacle x1="7.89" y1="5.189999999999999" x2="7.829999999999999" y2="5.249999999999999"/>
  <obstacle x1="7.95" y1="5.189999999999999" x2="7.89" y2="5.249999999999999"/>
  <obstacle x1="8.009999999999998" y1="5.189999999999999" x2="7.949999999999998" y2="5.249999999999999"/>
  <obstacle x1="8.069999999999999" y1="5.189999999999999" x2="8.01" y2="5.249999999999999"/>
  <obstacle x1="8.129999999999999" y1="5.189999999999999" x2="8.07" y2="5.249999999999999"/>
  <obstacle x1="8.19" y1="5.189999999999999" x2="8.13" y2="5.249999999999999"/>
  <obstacle x1="8.249999999999998" y1="5.189999999999999" x2="8.19" y2="5.249999999999999"/>
  <obstacle x1="8.309999999999999" y1="5.189999999999999" x2="8.25" y2="5.249999999999999"/>
  <obstacle x1="8.37" y1="5.189999999999999" x2="8.31" y2="5.249999999999999"/>
  <obstacle x1="8.429999999999998" y1="5.189999999999999" x2="8.37" y2="5.249999999999999"/>
  <obstacle x1="8.489999999999998" y1="5.189999999999999" x2="8.43" y2="5.249999999999999"/>
  <obstacle x1="8.549999999999999" y1="5.189999999999999" x2="8.49" y2="5.249999999999999"/>
  <obstacle x1="-5.91" y1="5.13" x2="-5.970000000000001" y2="5.19"/>
  <obstacle x1="1.5899999999999996" y1="5.13" x2="1.5299999999999996" y2="5.19"/>
  <obstacle x1="4.409999999999999" y1="5.13" x2="4.349999999999999" y2="5.19"/>
  <obstacle x1="8.549999999999999" y1="5.13" x2="8.49" y2="5.19"/>
  <obstacle x1="-5.91" y1="5.069999999999999" x2="-5.970000000000001" y2="5.13"/>
  <obstacle x1="1.5899999999999996" y1="5.069999999999999" x2="1.5299999999999996" y2="5.13"/>
  <obstacle x1="8.549999999999999" y1="5.069999999999999" x2="8.49" y2="5.13"/>
  <obstacle x1="-5.91" y1="5.009999999999999" x2="-5.970000000000001" y2="5.069999999999999"/>
  <obstacle x1="1.5899999999999996" y1="5.009999999999999" x2="1.5299999999999996" y2="5.069999999999999"/>
  <obstacle x1="8.549999999999999" y1="5.009999999999999" x2="8.49" y2="5.069999999999999"/>
  <obstacle x1="-5.91" y1="4.95" x2="-5.970000000000001" y2="5.010000000000001"/>
  <obstacle x1="8.549999999999999" y1="4.95" x2="8.49" y2="5.010000000000001"/>
  <obstacle x1="-5.91" y1="4.89" x2="-5.970000000000001" y2="4.95"/>
  <obstacle x1="8.549999999999999" y1="4.89" x2="8.49" y2="4.95"/>
  <obstacle x1="-5.91" y1="4.829999999999999" x2="-5.970000000000001" y2="4.89"/>
  <obstacle x1="8.549999999999999" y1="4.829999999999999" x2="8.49" y2="4.89"/>
  <obstacle x1="-5.91" y1="4.769999999999999" x2="-5.970000000000001" y2="4.829999999999999"/>
  <obstacle x1="3.2099999999999995" y1="4.769999999999999" x2="3.15" y2="4.829999999999999"/>
  <obstacle x1="8.549999999999999" y1="4.769999999999999" x2="8.49" y2="4.829999999999999"/>
  <obstacle x1="-5.91" y1="4.71" x2="-5.970000000000001" y2="4.7700000000000005"/>
  <obstacle x1="1.6500000000000001" y1="4.71" x2="1.59" y2="4.7700000000000005"/>
  <obstacle x1="1.7099999999999997" y1="4.71" x2="1.6499999999999997" y2="4.7700000000000005"/>
  <obstacle x1="8.549999999999999" y1="4.71" x2="8.49" y2="4.7700000000000005"/>
  <obstacle x1="-5.91" y1="4.6499999999999995" x2="-5.970000000000001" y2="4.71"/>
  <obstacle x1="8.549999999999999" y1="4.6499999999999995" x2="8.49" y2="4.71"/>
  <obstacle x1="-5.91" y1="4.589999999999999" x2="-5.970000000000001" y2="4.6499999999999995"/>
  <obstacle x1="2.7899999999999996" y1="4.589999999999999" x2="2.73" y2="4.6499999999999995"/>
  <obstacle x1="8.549999999999999" y1="4.589999999999999" x2="8.49" y2="4.6499999999999995"/>
  <obstacle x1="-5.91" y1="4.5299999999999985" x2="-5.970000000000001" y2="4.589999999999999"/>
  <obstacle x1="8.549999999999999" y1="4.5299999999999985" x2="8.49" y2="4.589999999999999"/>
  <obstacle x1="-5.91" y1="4.47" x2="-5.970000000000001" y2="4.53"/>
  <obstacle x1="1.6500000000000001" y1="4.47" x2="1.59" y2="4.53"/>
  <obstacle x1="1.7099999999999997" y1="4.47" x2="1.6499999999999997" y2="4.53"/>
  <obstacle x1="1.7699999999999994" y1="4.47" x2="1.7099999999999993" y2="4.53"/>
  <obstacle x1="8.549999999999999" y1="4.47" x2="8.49" y2="4.53"/>
  <obstacle x1="-5.91" y1="4.409999999999999" x2="-5.970000000000001" y2="4.47"/>
  <obstacle x1="2.729999999999999" y1="4.409999999999999" x2="2.6699999999999995" y2="4.47"/>
  <obstacle x1="2.7899999999999996" y1="4.409999999999999" x2="2.73" y2="4.47"/>
  <obstacle x1="7.169999999999999" y1="4.409999999999999" x2="7.1099999999999985" y2="4.47"/>
  <obstacle x1="8.549999999999999" y1="4.409999999999999" x2="8.49" y2="4.47"/>
  <obstacle x1="-5.91" y1="4.349999999999999" x2="-5.970000000000001" y2="4.409999999999999"/>
  <obstacle x1="8.549999999999999" y1="4.349999999999999" x2="8.49" y2="4.409999999999999"/>
  <obstacle x1="-5.91" y1="4.29" x2="-5.970000000000001" y2="4.3500000000000005"/>
  <obstacle x1="8.549999999999999" y1="4.29" x2="8.49" y2="4.3500000000000005"/>
  <obstacle x1="-5.91" y1="4.2299999999999995" x2="-5.970000000000001" y2="4.29"/>
  <obstacle x1="8.549999999999999" y1="4.2299999999999995" x2="8.49" y2="4.29"/>
  <obstacle x1="-5.91" y1="4.169999999999999" x2="-5.970000000000001" y2="4.2299999999999995"/>
  <obstacle x1="8.549999999999999" y1="4.169999999999999" x2="8.49" y2="4.2299999999999995"/>
  <obstacle x1="-5.91" y1="4.1099999999999985" x2="-5.970000000000001" y2="4.169999999999999"/>
  <obstacle x1="7.05" y1="4.1099999999999985" x2="6.989999999999999" y2="4.169999999999999"/>
  <obstacle x1="8.549999999999999" y1="4.1099999999999985" x2="8.49" y2="4.169999999999999"/>
  <obstacle x1="-5.91" y1="4.05" x2="-5.970000000000001" y2="4.11"/>
  <obstacle x1="8.549999999999999" y1="4.05" x2="8.49" y2="4.11"/>
  <obstacle x1="-5.91" y1="3.9899999999999998" x2="-5.970000000000001" y2="4.05"/>
  <obstacle x1="8.549999999999999" y1="3.9899999999999998" x2="8.49" y2="4.05"/>
  <obstacle x1="-5.91" y1="3.9299999999999993" x2="-5.970000000000001" y2="3.989999999999999"/>
  <obstacle x1="8.549999999999999" y1="3.9299999999999993" x2="8.49" y2="3.989999999999999"/>
  <obstacle x1="-5.91" y1="3.8700000000000006" x2="-5.970000000000001" y2="3.93"/>
  <obstacle x1="7.2299999999999995" y1="3.8700000000000006" x2="7.169999999999999" y2="3.93"/>
  <obstacle x1="8.549999999999999" y1="3.8700000000000006" x2="8.49" y2="3.93"/>
  <obstacle x1="-5.91" y1="3.81" x2="-5.970000000000001" y2="3.8699999999999997"/>
  <obstacle x1="7.05" y1="3.81" x2="6.989999999999999" y2="3.8699999999999997"/>
  <obstacle x1="7.2299999999999995" y1="3.81" x2="7.169999999999999" y2="3.8699999999999997"/>
  <obstacle x1="8.549999999999999" y1="3.81" x2="8.49" y2="3.8699999999999997"/>
  <obstacle x1="-5.91" y1="3.7499999999999996" x2="-5.970000000000001" y2="3.809999999999999"/>
  <obstacle x1="7.2299999999999995" y1="3.7499999999999996" x2="7.169999999999999" y2="3.809999999999999"/>
  <obstacle x1="8.549999999999999" y1="3.7499999999999996" x2="8.49" y2="3.809999999999999"/>
  <obstacle x1="-5.91" y1="3.689999999999999" x2="-5.970000000000001" y2="3.7499999999999987"/>
  <obstacle x1="7.2299999999999995" y1="3.689999999999999" x2="7.169999999999999" y2="3.7499999999999987"/>
  <obstacle x1="8.549999999999999" y1="3.689999999999999" x2="8.49" y2="3.7499999999999987"/>
  <obstacle x1="-5.91" y1="3.6300000000000003" x2="-5.970000000000001" y2="3.69"/>
  <obstacle x1="8.549999999999999" y1="3.6300000000000003" x2="8.49" y2="3.69"/>
  <obstacle x1="-5.91" y1="3.57" x2="-5.970000000000001" y2="3.6299999999999994"/>
  <obstacle x1="7.29" y1="3.57" x2="7.2299999999999995" y2="3.6299999999999994"/>
  <obstacle x1="8.549999999999999" y1="3.57" x2="8.49" y2="3.6299999999999994"/>
  <obstacle x1="-5.91" y1="3.5099999999999993" x2="-5.970000000000001" y2="3.569999999999999"/>
  <obstacle x1="7.29" y1="3.5099999999999993" x2="7.2299999999999995" y2="3.569999999999999"/>
  <obstacle x1="8.549999999999999" y1="3.5099999999999993" x2="8.49" y2="3.569999999999999"/>
  <obstacle x1="-5.91" y1="3.4500000000000006" x2="-5.970000000000001" y2="3.5100000000000002"/>
  <obstacle x1="8.549999999999999" y1="3.4500000000000006" x2="8.49" y2="3.5100000000000002"/>
  <obstacle x1="-5.91" y1="3.39" x2="-5.970000000000001" y2="3.4499999999999997"/>
  <obstacle x1="8.549999999999999" y1="3.39" x2="8.49" y2="3.4499999999999997"/>
  <obstacle x1="-5.91" y1="3.3299999999999996" x2="-5.970000000000001" y2="3.3899999999999992"/>
  <obstacle x1="8.549999999999999" y1="3.3299999999999996" x2="8.49" y2="3.3899999999999992"/>
  <obstacle x1="-5.91" y1="3.269999999999999" x2="-5.970000000000001" y2="3.3299999999999987"/>
  <obstacle x1="8.549999999999999" y1="3.269999999999999" x2="8.49" y2="3.3299999999999987"/>
  <obstacle x1="-5.91" y1="3.2100000000000004" x2="-5.970000000000001" y2="3.27"/>
  <obstacle x1="8.549999999999999" y1="3.2100000000000004" x2="8.49" y2="3.27"/>
  <obstacle x1="-5.91" y1="3.15" x2="-5.970000000000001" y2="3.2099999999999995"/>
  <obstacle x1="8.549999999999999" y1="3.15" x2="8.49" y2="3.2099999999999995"/>
  <obstacle x1="-5.91" y1="3.0899999999999994" x2="-5.970000000000001" y2="3.149999999999999"/>
  <obstacle x1="7.95" y1="3.0899999999999994" x2="7.89" y2="3.149999999999999"/>
  <obstacle x1="8.489999999999998" y1="3.0899999999999994" x2="8.43" y2="3.149999999999999"/>
  <obstacle x1="8.549999999999999" y1="3.0899999999999994" x2="8.49" y2="3.149999999999999"/>
  <obstacle x1="-5.91" y1="3.0300000000000007" x2="-5.970000000000001" y2="3.0900000000000003"/>
  <obstacle x1="8.549999999999999" y1="3.0300000000000007" x2="8.49" y2="3.0900000000000003"/>
  <obstacle x1="-5.91" y1="2.97" x2="-5.970000000000001" y2="3.03"/>
  <obstacle x1="8.549999999999999" y1="2.97" x2="8.49" y2="3.03"/>
  <obstacle x1="-5.91" y1="2.9099999999999997" x2="-5.970000000000001" y2="2.9699999999999993"/>
  <obstacle x1="8.549999999999999" y1="2.9099999999999997" x2="8.49" y2="2.9699999999999993"/>
  <obstacle x1="-5.91" y1="2.849999999999999" x2="-5.970000000000001" y2="2.909999999999999"/>
  <obstacle x1="8.549999999999999" y1="2.849999999999999" x2="8.49" y2="2.909999999999999"/>
  <obstacle x1="-5.91" y1="2.7900000000000005" x2="-5.970000000000001" y2="2.85"/>
  <obstacle x1="8.549999999999999" y1="2.7900000000000005" x2="8.49" y2="2.85"/>
  <obstacle x1="-5.91" y1="2.73" x2="-5.970000000000001" y2="2.7899999999999996"/>
  <obstacle x1="8.549999999999999" y1="2.73" x2="8.49" y2="2.7899999999999996"/>
  <obstacle x1="-5.91" y1="2.6699999999999995" x2="-5.970000000000001" y2="2.729999999999999"/>
  <obstacle x1="8.549999999999999" y1="2.6699999999999995" x2="8.49" y2="2.729999999999999"/>
  <obstacle x1="-5.91" y1="2.6100000000000008" x2="-5.970000000000001" y2="2.6700000000000004"/>
  <obstacle x1="8.549999999999999" y1="2.6100000000000008" x2="8.49" y2="2.6700000000000004"/>
  <obstacle x1="-5.91" y1="2.5500000000000003" x2="-5.970000000000001" y2="2.61"/>
  <obstacle x1="8.549999999999999" y1="2.5500000000000003" x2="8.49" y2="2.61"/>
  <obstacle x1="-5.91" y1="2.4899999999999998" x2="-5.970000000000001" y2="2.5499999999999994"/>
  <obstacle x1="8.549999999999999" y1="2.4899999999999998" x2="8.49" y2="2.5499999999999994"/>
  <obstacle x1="-5.91" y1="2.4299999999999993" x2="-5.970000000000001" y2="2.489999999999999"/>
  <obstacle x1="8.549999999999999" y1="2.4299999999999993" x2="8.49" y2="2.489999999999999"/>
  <obstacle x1="-5.91" y1="2.3700000000000006" x2="-5.970000000000001" y2="2.43"/>
  <obstacle x1="8.549999999999999" y1="2.3700000000000006" x2="8.49" y2="2.43"/>
  <obstacle x1="-5.91" y1="2.31" x2="-5.970000000000001" y2="2.3699999999999997"/>
  <obstacle x1="8.549999999999999" y1="2.31" x2="8.49" y2="2.3699999999999997"/>
  <obstacle x1="-5.91" y1="2.2499999999999996" x2="-5.970000000000001" y2="2.309999999999999"/>
  <obstacle x1="8.549999999999999" y1="2.2499999999999996" x2="8.49" y2="2.309999999999999"/>
  <obstacle x1="-5.91" y1="2.189999999999999" x2="-5.970000000000001" y2="2.2499999999999987"/>
  <obstacle x1="8.549999999999999" y1="2.189999999999999" x2="8.49" y2="2.2499999999999987"/>
  <obstacle x1="-5.91" y1="2.1300000000000003" x2="-5.970000000000001" y2="2.19"/>
  <obstacle x1="8.549999999999999" y1="2.1300000000000003" x2="8.49" y2="2.19"/>
  <obstacle x1="-5.91" y1="2.07" x2="-5.970000000000001" y2="2.1299999999999994"/>
  <obstacle x1="8.549999999999999" y1="2.07" x2="8.49" y2="2.1299999999999994"/>
  <obstacle x1="-5.91" y1="2.0099999999999993" x2="-5.970000000000001" y2="2.069999999999999"/>
  <obstacle x1="8.549999999999999" y1="2.0099999999999993" x2="8.49" y2="2.069999999999999"/>
  <obstacle x1="-5.91" y1="1.9499999999999995" x2="-5.970000000000001" y2="2.0099999999999993"/>
  <obstacle x1="8.549999999999999" y1="1.9499999999999995" x2="8.49" y2="2.0099999999999993"/>
  <obstacle x1="-5.91" y1="1.89" x2="-5.970000000000001" y2="1.95"/>
  <obstacle x1="8.549999999999999" y1="1.89" x2="8.49" y2="1.95"/>
  <obstacle x1="-5.91" y1="1.8299999999999994" x2="-5.970000000000001" y2="1.8899999999999995"/>
  <obstacle x1="8.549999999999999" y1="1.8299999999999994" x2="8.49" y2="1.8899999999999995"/>
  <obstacle x1="-5.91" y1="1.7699999999999998" x2="-5.970000000000001" y2="1.8299999999999998"/>
  <obstacle x1="8.549999999999999" y1="1.7699999999999998" x2="8.49" y2="1.8299999999999998"/>
  <obstacle x1="-5.91" y1="1.7099999999999993" x2="-5.970000000000001" y2="1.7699999999999994"/>
  <obstacle x1="8.549999999999999" y1="1.7099999999999993" x2="8.49" y2="1.7699999999999994"/>
  <obstacle x1="-5.91" y1="1.6499999999999997" x2="-5.970000000000001" y2="1.7099999999999997"/>
  <obstacle x1="8.549999999999999" y1="1.6499999999999997" x2="8.49" y2="1.7099999999999997"/>
  <obstacle x1="-5.91" y1="1.59" x2="-5.970000000000001" y2="1.6500000000000001"/>
  <obstacle x1="8.549999999999999" y1="1.59" x2="8.49" y2="1.6500000000000001"/>
  <obstacle x1="-5.91" y1="1.5299999999999996" x2="-5.970000000000001" y2="1.5899999999999996"/>
  <obstacle x1="8.549999999999999" y1="1.5299999999999996" x2="8.49" y2="1.5899999999999996"/>
  <obstacle x1="-5.91" y1="1.47" x2="-5.970000000000001" y2="1.53"/>
  <obstacle x1="8.549999999999999" y1="1.47" x2="8.49" y2="1.53"/>
  <obstacle x1="-5.91" y1="1.4099999999999995" x2="-5.970000000000001" y2="1.4699999999999995"/>
  <obstacle x1="8.549999999999999" y1="1.4099999999999995" x2="8.49" y2="1.4699999999999995"/>
  <obstacle x1="-5.91" y1="1.3499999999999999" x2="-5.970000000000001" y2="1.41"/>
  <obstacle x1="8.549999999999999" y1="1.3499999999999999" x2="8.49" y2="1.41"/>
  <obstacle x1="-5.91" y1="1.2899999999999994" x2="-5.970000000000001" y2="1.3499999999999994"/>
  <obstacle x1="8.549999999999999" y1="1.2899999999999994" x2="8.49" y2="1.3499999999999994"/>
  <obstacle x1="-5.91" y1="1.2299999999999998" x2="-5.970000000000001" y2="1.2899999999999998"/>
  <obstacle x1="8.549999999999999" y1="1.2299999999999998" x2="8.49" y2="1.2899999999999998"/>
  <obstacle x1="-5.91" y1="1.1699999999999993" x2="-5.970000000000001" y2="1.2299999999999993"/>
  <obstacle x1="8.549999999999999" y1="1.1699999999999993" x2="8.49" y2="1.2299999999999993"/>
  <obstacle x1="-5.91" y1="1.1099999999999997" x2="-5.970000000000001" y2="1.1699999999999997"/>
  <obstacle x1="8.549999999999999" y1="1.1099999999999997" x2="8.49" y2="1.1699999999999997"/>
  <obstacle x1="-5.91" y1="1.05" x2="-5.970000000000001" y2="1.11"/>
  <obstacle x1="8.549999999999999" y1="1.05" x2="8.49" y2="1.11"/>
  <obstacle x1="-5.91" y1="0.9899999999999995" x2="-5.970000000000001" y2="1.0499999999999996"/>
  <obstacle x1="8.549999999999999" y1="0.9899999999999995" x2="8.49" y2="1.0499999999999996"/>
  <obstacle x1="-5.91" y1="0.9299999999999999" x2="-5.970000000000001" y2="0.99"/>
  <obstacle x1="8.549999999999999" y1="0.9299999999999999" x2="8.49" y2="0.99"/>
  <obstacle x1="-5.91" y1="0.8699999999999994" x2="-5.970000000000001" y2="0.9299999999999995"/>
  <obstacle x1="8.549999999999999" y1="0.8699999999999994" x2="8.49" y2="0.9299999999999995"/>
  <obstacle x1="-5.91" y1="0.8099999999999998" x2="-5.970000000000001" y2="0.8699999999999999"/>
  <obstacle x1="8.549999999999999" y1="0.8099999999999998" x2="8.49" y2="0.8699999999999999"/>
  <obstacle x1="-5.91" y1="0.7499999999999993" x2="-5.970000000000001" y2="0.8099999999999994"/>
  <obstacle x1="-5.43" y1="0.7499999999999993" x2="-5.49" y2="0.8099999999999994"/>
  <obstacle x1="-5.25" y1="0.7499999999999993" x2="-5.3100000000000005" y2="0.8099999999999994"/>
  <obstacle x1="8.549999999999999" y1="0.7499999999999993" x2="8.49" y2="0.8099999999999994"/>
  <obstacle x1="-5.91" y1="0.6899999999999997" x2="-5.970000000000001" y2="0.7499999999999998"/>
  <obstacle x1="8.549999999999999" y1="0.6899999999999997" x2="8.49" y2="0.7499999999999998"/>
  <obstacle x1="-5.91" y1="0.6300000000000001" x2="-5.970000000000001" y2="0.6900000000000002"/>
  <obstacle x1="8.549999999999999" y1="0.6300000000000001" x2="8.49" y2="0.6900000000000002"/>
  <obstacle x1="-5.91" y1="0.5699999999999996" x2="-5.970000000000001" y2="0.6299999999999997"/>
  <obstacle x1="8.549999999999999" y1="0.5699999999999996" x2="8.49" y2="0.6299999999999997"/>
  <obstacle x1="-5.91" y1="0.51" x2="-5.970000000000001" y2="0.5700000000000001"/>
  <obstacle x1="8.549999999999999" y1="0.51" x2="8.49" y2="0.5700000000000001"/>
  <obstacle x1="-5.91" y1="0.4499999999999995" x2="-5.970000000000001" y2="0.5099999999999996"/>
  <obstacle x1="8.549999999999999" y1="0.4499999999999995" x2="8.49" y2="0.5099999999999996"/>
  <obstacle x1="-5.91" y1="0.3899999999999999" x2="-5.970000000000001" y2="0.44999999999999996"/>
  <obstacle x1="8.549999999999999" y1="0.3899999999999999" x2="8.49" y2="0.44999999999999996"/>
  <obstacle x1="-5.91" y1="0.3299999999999994" x2="-5.970000000000001" y2="0.38999999999999946"/>
  <obstacle x1="8.549999999999999" y1="0.3299999999999994" x2="8.49" y2="0.38999999999999946"/>
  <obstacle x1="-5.91" y1="0.2699999999999998" x2="-5.970000000000001" y2="0.32999999999999985"/>
  <obstacle x1="8.549999999999999" y1="0.2699999999999998" x2="8.49" y2="0.32999999999999985"/>
  <obstacle x1="-5.91" y1="0.21000000000000021" x2="-5.970000000000001" y2="0.27000000000000024"/>
  <obstacle x1="8.549999999999999" y1="0.21000000000000021" x2="8.49" y2="0.27000000000000024"/>
  <obstacle x1="-5.91" y1="0.14999999999999972" x2="-5.970000000000001" y2="0.20999999999999971"/>
  <obstacle x1="8.549999999999999" y1="0.14999999999999972" x2="8.49" y2="0.20999999999999971"/>
  <obstacle x1="-5.91" y1="0.09000000000000011" x2="-5.970000000000001" y2="0.1500000000000001"/>
  <obstacle x1="8.549999999999999" y1="0.09000000000000011" x2="8.49" y2="0.1500000000000001"/>
  <obstacle x1="-5.91" y1="0.02999999999999961" x2="-5.970000000000001" y2="0.08999999999999961"/>
  <obstacle x1="8.549999999999999" y1="0.02999999999999961" x2="8.49" y2="0.08999999999999961"/>
  <obstacle x1="-5.91" y1="-0.03" x2="-5.970000000000001" y2="0.03"/>
  <obstacle x1="8.549999999999999" y1="-0.03" x2="8.49" y2="0.03"/>
  <obstacle x1="-5.91" y1="-0.0900000000000005" x2="-5.970000000000001" y2="-0.0300000000000005"/>
  <obstacle x1="8.549999999999999" y1="-0.0900000000000005" x2="8.49" y2="-0.0300000000000005"/>
  <obstacle x1="-5.91" y1="-0.1500000000000001" x2="-5.970000000000001" y2="-0.09000000000000011"/>
  <obstacle x1="2.729999999999999" y1="-0.1500000000000001" x2="2.6699999999999995" y2="-0.09000000000000011"/>
  <obstacle x1="2.9699999999999993" y1="-0.1500000000000001" x2="2.9099999999999997" y2="-0.09000000000000011"/>
  <obstacle x1="8.549999999999999" y1="-0.1500000000000001" x2="8.49" y2="-0.09000000000000011"/>
  <obstacle x1="-5.91" y1="-0.2100000000000006" x2="-5.970000000000001" y2="-0.1500000000000006"/>
  <obstacle x1="2.729999999999999" y1="-0.2100000000000006" x2="2.6699999999999995" y2="-0.1500000000000006"/>
  <obstacle x1="2.9699999999999993" y1="-0.2100000000000006" x2="2.9099999999999997" y2="-0.1500000000000006"/>
  <obstacle x1="8.549999999999999" y1="-0.2100000000000006" x2="8.49" y2="-0.1500000000000006"/>
  <obstacle x1="-5.91" y1="-0.27000000000000024" x2="-5.970000000000001" y2="-0.21000000000000021"/>
  <obstacle x1="8.549999999999999" y1="-0.27000000000000024" x2="8.49" y2="-0.21000000000000021"/>
  <obstacle x1="-5.91" y1="-0.32999999999999985" x2="-5.970000000000001" y2="-0.2699999999999998"/>
  <obstacle x1="8.549999999999999" y1="-0.32999999999999985" x2="8.49" y2="-0.2699999999999998"/>
  <obstacle x1="-5.91" y1="-0.39000000000000035" x2="-5.970000000000001" y2="-0.3300000000000003"/>
  <obstacle x1="-5.13" y1="-0.39000000000000035" x2="-5.19" y2="-0.3300000000000003"/>
  <obstacle x1="-5.01" y1="-0.39000000000000035" x2="-5.07" y2="-0.3300000000000003"/>
  <obstacle x1="8.549999999999999" y1="-0.39000000000000035" x2="8.49" y2="-0.3300000000000003"/>
  <obstacle x1="-5.91" y1="-0.44999999999999996" x2="-5.970000000000001" y2="-0.3899999999999999"/>
  <obstacle x1="-5.01" y1="-0.44999999999999996" x2="-5.07" y2="-0.3899999999999999"/>
  <obstacle x1="8.549999999999999" y1="-0.44999999999999996" x2="8.49" y2="-0.3899999999999999"/>
  <obstacle x1="-5.91" y1="-0.5100000000000005" x2="-5.970000000000001" y2="-0.4500000000000004"/>
  <obstacle x1="8.549999999999999" y1="-0.5100000000000005" x2="8.49" y2="-0.4500000000000004"/>
  <obstacle x1="-5.91" y1="-0.5700000000000001" x2="-5.970000000000001" y2="-0.51"/>
  <obstacle x1="-5.01" y1="-0.5700000000000001" x2="-5.07" y2="-0.51"/>
  <obstacle x1="8.549999999999999" y1="-0.5700000000000001" x2="8.49" y2="-0.51"/>
  <obstacle x1="-5.91" y1="-0.6300000000000006" x2="-5.970000000000001" y2="-0.5700000000000005"/>
  <obstacle x1="8.549999999999999" y1="-0.6300000000000006" x2="8.49" y2="-0.5700000000000005"/>
  <obstacle x1="-5.91" y1="-0.6900000000000002" x2="-5.970000000000001" y2="-0.6300000000000001"/>
  <obstacle x1="2.0099999999999993" y1="-0.6900000000000002" x2="1.9499999999999995" y2="-0.6300000000000001"/>
  <obstacle x1="3.69" y1="-0.6900000000000002" x2="3.6300000000000003" y2="-0.6300000000000001"/>
  <obstacle x1="8.549999999999999" y1="-0.6900000000000002" x2="8.49" y2="-0.6300000000000001"/>
  <obstacle x1="-5.91" y1="-0.7500000000000007" x2="-5.970000000000001" y2="-0.6900000000000006"/>
  <obstacle x1="8.549999999999999" y1="-0.7500000000000007" x2="8.49" y2="-0.6900000000000006"/>
  <obstacle x1="-5.91" y1="-0.8100000000000003" x2="-5.970000000000001" y2="-0.7500000000000002"/>
  <obstacle x1="-5.069999999999999" y1="-0.8100000000000003" x2="-5.13" y2="-0.7500000000000002"/>
  <obstacle x1="8.549999999999999" y1="-0.8100000000000003" x2="8.49" y2="-0.7500000000000002"/>
  <obstacle x1="-5.91" y1="-0.8699999999999999" x2="-5.970000000000001" y2="-0.8099999999999998"/>
  <obstacle x1="-5.069999999999999" y1="-0.8699999999999999" x2="-5.13" y2="-0.8099999999999998"/>
  <obstacle x1="2.0099999999999993" y1="-0.8699999999999999" x2="1.9499999999999995" y2="-0.8099999999999998"/>
  <obstacle x1="3.69" y1="-0.8699999999999999" x2="3.6300000000000003" y2="-0.8099999999999998"/>
  <obstacle x1="8.549999999999999" y1="-0.8699999999999999" x2="8.49" y2="-0.8099999999999998"/>
  <obstacle x1="-5.91" y1="-0.9300000000000004" x2="-5.970000000000001" y2="-0.8700000000000003"/>
  <obstacle x1="-5.069999999999999" y1="-0.9300000000000004" x2="-5.13" y2="-0.8700000000000003"/>
  <obstacle x1="8.549999999999999" y1="-0.9300000000000004" x2="8.49" y2="-0.8700000000000003"/>
  <obstacle x1="-5.91" y1="-0.99" x2="-5.970000000000001" y2="-0.9299999999999999"/>
  <obstacle x1="8.549999999999999" y1="-0.99" x2="8.49" y2="-0.9299999999999999"/>
  <obstacle x1="-5.91" y1="-1.0500000000000005" x2="-5.970000000000001" y2="-0.9900000000000004"/>
  <obstacle x1="8.549999999999999" y1="-1.0500000000000005" x2="8.49" y2="-0.9900000000000004"/>
  <obstacle x1="-5.91" y1="-1.11" x2="-5.970000000000001" y2="-1.05"/>
  <obstacle x1="8.549999999999999" y1="-1.11" x2="8.49" y2="-1.05"/>
  <obstacle x1="-5.91" y1="-1.1700000000000006" x2="-5.970000000000001" y2="-1.1100000000000005"/>
  <obstacle x1="8.549999999999999" y1="-1.1700000000000006" x2="8.49" y2="-1.1100000000000005"/>
  <obstacle x1="-5.91" y1="-1.2300000000000002" x2="-5.970000000000001" y2="-1.1700000000000002"/>
  <obstacle x1="8.549999999999999" y1="-1.2300000000000002" x2="8.49" y2="-1.1700000000000002"/>
  <obstacle x1="-5.91" y1="-1.2899999999999998" x2="-5.970000000000001" y2="-1.2299999999999998"/>
  <obstacle x1="-5.01" y1="-1.2899999999999998" x2="-5.07" y2="-1.2299999999999998"/>
  <obstacle x1="2.489999999999999" y1="-1.2899999999999998" x2="2.4299999999999993" y2="-1.2299999999999998"/>
  <obstacle x1="8.549999999999999" y1="-1.2899999999999998" x2="8.49" y2="-1.2299999999999998"/>
  <obstacle x1="-5.91" y1="-1.3500000000000003" x2="-5.970000000000001" y2="-1.2900000000000003"/>
  <obstacle x1="-5.01" y1="-1.3500000000000003" x2="-5.07" y2="-1.2900000000000003"/>
  <obstacle x1="2.9699999999999993" y1="-1.3500000000000003" x2="2.9099999999999997" y2="-1.2900000000000003"/>
  <obstacle x1="8.549999999999999" y1="-1.3500000000000003" x2="8.49" y2="-1.2900000000000003"/>
  <obstacle x1="-5.91" y1="-1.41" x2="-5.970000000000001" y2="-1.3499999999999999"/>
  <obstacle x1="2.6700000000000004" y1="-1.41" x2="2.6100000000000008" y2="-1.3499999999999999"/>
  <obstacle x1="2.729999999999999" y1="-1.41" x2="2.6699999999999995" y2="-1.3499999999999999"/>
  <obstacle x1="2.9699999999999993" y1="-1.41" x2="2.9099999999999997" y2="-1.3499999999999999"/>
  <obstacle x1="3.03" y1="-1.41" x2="2.97" y2="-1.3499999999999999"/>
  <obstacle x1="8.549999999999999" y1="-1.41" x2="8.49" y2="-1.3499999999999999"/>
  <obstacle x1="-5.91" y1="-1.4700000000000004" x2="-5.970000000000001" y2="-1.4100000000000004"/>
  <obstacle x1="8.549999999999999" y1="-1.4700000000000004" x2="8.49" y2="-1.4100000000000004"/>
  <obstacle x1="-5.91" y1="-1.53" x2="-5.970000000000001" y2="-1.47"/>
  <obstacle x1="8.549999999999999" y1="-1.53" x2="8.49" y2="-1.47"/>
  <obstacle x1="-5.91" y1="-1.5900000000000005" x2="-5.970000000000001" y2="-1.5300000000000005"/>
  <obstacle x1="8.549999999999999" y1="-1.5900000000000005" x2="8.49" y2="-1.5300000000000005"/>
  <obstacle x1="-5.91" y1="-1.6500000000000001" x2="-5.970000000000001" y2="-1.59"/>
  <obstacle x1="8.549999999999999" y1="-1.6500000000000001" x2="8.49" y2="-1.59"/>
  <obstacle x1="-5.91" y1="-1.7099999999999997" x2="-5.970000000000001" y2="-1.6499999999999997"/>
  <obstacle x1="8.549999999999999" y1="-1.7099999999999997" x2="8.49" y2="-1.6499999999999997"/>
  <obstacle x1="-5.91" y1="-1.7700000000000002" x2="-5.970000000000001" y2="-1.7100000000000002"/>
  <obstacle x1="8.549999999999999" y1="-1.7700000000000002" x2="8.49" y2="-1.7100000000000002"/>
  <obstacle x1="-5.91" y1="-1.8299999999999998" x2="-5.970000000000001" y2="-1.7699999999999998"/>
  <obstacle x1="8.549999999999999" y1="-1.8299999999999998" x2="8.49" y2="-1.7699999999999998"/>
  <obstacle x1="-5.91" y1="-1.8900000000000003" x2="-5.970000000000001" y2="-1.8300000000000003"/>
  <obstacle x1="8.549999999999999" y1="-1.8900000000000003" x2="8.49" y2="-1.8300000000000003"/>
  <obstacle x1="-5.91" y1="-1.95" x2="-5.970000000000001" y2="-1.89"/>
  <obstacle x1="8.549999999999999" y1="-1.95" x2="8.49" y2="-1.89"/>
  <obstacle x1="-5.91" y1="-2.0100000000000002" x2="-5.970000000000001" y2="-1.9500000000000004"/>
  <obstacle x1="8.549999999999999" y1="-2.0100000000000002" x2="8.49" y2="-1.9500000000000004"/>
  <obstacle x1="-5.91" y1="-2.07" x2="-5.970000000000001" y2="-2.0100000000000002"/>
  <obstacle x1="8.549999999999999" y1="-2.07" x2="8.49" y2="-2.0100000000000002"/>
  <obstacle x1="-5.91" y1="-2.13" x2="-5.970000000000001" y2="-2.0700000000000003"/>
  <obstacle x1="8.549999999999999" y1="-2.13" x2="8.49" y2="-2.0700000000000003"/>
  <obstacle x1="-5.91" y1="-2.19" x2="-5.970000000000001" y2="-2.1300000000000003"/>
  <obstacle x1="8.549999999999999" y1="-2.19" x2="8.49" y2="-2.1300000000000003"/>
  <obstacle x1="-5.91" y1="-2.25" x2="-5.970000000000001" y2="-2.1900000000000004"/>
  <obstacle x1="8.549999999999999" y1="-2.25" x2="8.49" y2="-2.1900000000000004"/>
  <obstacle x1="-5.91" y1="-2.31" x2="-5.970000000000001" y2="-2.2500000000000004"/>
  <obstacle x1="8.549999999999999" y1="-2.31" x2="8.49" y2="-2.2500000000000004"/>
  <obstacle x1="-5.91" y1="-2.37" x2="-5.970000000000001" y2="-2.3100000000000005"/>
  <obstacle x1="8.549999999999999" y1="-2.37" x2="8.49" y2="-2.3100000000000005"/>
  <obstacle x1="-5.91" y1="-2.43" x2="-5.970000000000001" y2="-2.3700000000000006"/>
  <obstacle x1="8.549999999999999" y1="-2.43" x2="8.49" y2="-2.3700000000000006"/>
  <obstacle x1="-5.91" y1="-2.4899999999999998" x2="-5.970000000000001" y2="-2.43"/>
  <obstacle x1="8.549999999999999" y1="-2.4899999999999998" x2="8.49" y2="-2.43"/>
  <obstacle x1="-5.91" y1="-2.55" x2="-5.970000000000001" y2="-2.49"/>
  <obstacle x1="6.03" y1="-2.55" x2="5.97" y2="-2.49"/>
  <obstacle x1="8.549999999999999" y1="-2.55" x2="8.49" y2="-2.49"/>
  <obstacle x1="-5.91" y1="-2.61" x2="-5.970000000000001" y2="-2.5500000000000003"/>
  <obstacle x1="6.03" y1="-2.61" x2="5.97" y2="-2.5500000000000003"/>
  <obstacle x1="8.549999999999999" y1="-2.61" x2="8.49" y2="-2.5500000000000003"/>
  <obstacle x1="-5.91" y1="-2.67" x2="-5.970000000000001" y2="-2.6100000000000003"/>
  <obstacle x1="8.549999999999999" y1="-2.67" x2="8.49" y2="-2.6100000000000003"/>
  <obstacle x1="-5.91" y1="-2.73" x2="-5.970000000000001" y2="-2.6700000000000004"/>
  <obstacle x1="8.549999999999999" y1="-2.73" x2="8.49" y2="-2.6700000000000004"/>
  <obstacle x1="-5.91" y1="-2.79" x2="-5.970000000000001" y2="-2.7300000000000004"/>
  <obstacle x1="8.549999999999999" y1="-2.79" x2="8.49" y2="-2.7300000000000004"/>
  <obstacle x1="-5.91" y1="-2.85" x2="-5.970000000000001" y2="-2.7900000000000005"/>
  <obstacle x1="8.549999999999999" y1="-2.85" x2="8.49" y2="-2.7900000000000005"/>
  <obstacle x1="-5.91" y1="-2.9099999999999997" x2="-5.970000000000001" y2="-2.85"/>
  <obstacle x1="8.549999999999999" y1="-2.9099999999999997" x2="8.49" y2="-2.85"/>
  <obstacle x1="-5.91" y1="-2.9699999999999998" x2="-5.970000000000001" y2="-2.91"/>
  <obstacle x1="5.489999999999999" y1="-2.9699999999999998" x2="5.429999999999999" y2="-2.91"/>
  <obstacle x1="5.55" y1="-2.9699999999999998" x2="5.489999999999999" y2="-2.91"/>
  <obstacle x1="5.61" y1="-2.9699999999999998" x2="5.55" y2="-2.91"/>
  <obstacle x1="5.669999999999999" y1="-2.9699999999999998" x2="5.6099999999999985" y2="-2.91"/>
  <obstacle x1="5.7299999999999995" y1="-2.9699999999999998" x2="5.669999999999999" y2="-2.91"/>
  <obstacle x1="5.79" y1="-2.9699999999999998" x2="5.7299999999999995" y2="-2.91"/>
  <obstacle x1="8.549999999999999" y1="-2.9699999999999998" x2="8.49" y2="-2.91"/>
  <obstacle x1="-5.91" y1="-3.03" x2="-5.970000000000001" y2="-2.97"/>
  <obstacle x1="8.549999999999999" y1="-3.03" x2="8.49" y2="-2.97"/>
  <obstacle x1="-5.91" y1="-3.09" x2="-5.970000000000001" y2="-3.0300000000000002"/>
  <obstacle x1="8.549999999999999" y1="-3.09" x2="8.49" y2="-3.0300000000000002"/>
  <obstacle x1="-5.91" y1="-3.15" x2="-5.970000000000001" y2="-3.0900000000000003"/>
  <obstacle x1="8.549999999999999" y1="-3.15" x2="8.49" y2="-3.0900000000000003"/>
  <obstacle x1="-5.91" y1="-3.21" x2="-5.970000000000001" y2="-3.1500000000000004"/>
  <obstacle x1="8.549999999999999" y1="-3.21" x2="8.49" y2="-3.1500000000000004"/>
  <obstacle x1="-5.91" y1="-3.27" x2="-5.970000000000001" y2="-3.2100000000000004"/>
  <obstacle x1="8.549999999999999" y1="-3.27" x2="8.49" y2="-3.2100000000000004"/>
  <obstacle x1="-5.91" y1="-3.33" x2="-5.970000000000001" y2="-3.2700000000000005"/>
  <obstacle x1="8.549999999999999" y1="-3.33" x2="8.49" y2="-3.2700000000000005"/>
  <obstacle x1="-5.91" y1="-3.39" x2="-5.970000000000001" y2="-3.3300000000000005"/>
  <obstacle x1="5.249999999999999" y1="-3.39" x2="5.189999999999999" y2="-3.3300000000000005"/>
  <obstacle x1="8.549999999999999" y1="-3.39" x2="8.49" y2="-3.3300000000000005"/>
  <obstacle x1="-5.91" y1="-3.4499999999999997" x2="-5.970000000000001" y2="-3.39"/>
  <obstacle x1="5.249999999999999" y1="-3.4499999999999997" x2="5.189999999999999" y2="-3.39"/>
  <obstacle x1="8.549999999999999" y1="-3.4499999999999997" x2="8.49" y2="-3.39"/>
  <obstacle x1="-5.91" y1="-3.51" x2="-5.970000000000001" y2="-3.45"/>
  <obstacle x1="5.249999999999999" y1="-3.51" x2="5.189999999999999" y2="-3.45"/>
  <obstacle x1="8.549999999999999" y1="-3.51" x2="8.49" y2="-3.45"/>
  <obstacle x1="-5.91" y1="-3.57" x2="-5.970000000000001" y2="-3.5100000000000002"/>
  <obstacle x1="5.249999999999999" y1="-3.57" x2="5.189999999999999" y2="-3.5100000000000002"/>
  <obstacle x1="8.549999999999999" y1="-3.57" x2="8.49" y2="-3.5100000000000002"/>
  <obstacle x1="-5.91" y1="-3.63" x2="-5.970000000000001" y2="-3.5700000000000003"/>
  <obstacle x1="0.8699999999999999" y1="-3.63" x2="0.8099999999999998" y2="-3.5700000000000003"/>
  <obstacle x1="1.0499999999999996" y1="-3.63" x2="0.9899999999999995" y2="-3.5700000000000003"/>
  <obstacle x1="1.11" y1="-3.63" x2="1.05" y2="-3.5700000000000003"/>
  <obstacle x1="1.1699999999999997" y1="-3.63" x2="1.1099999999999997" y2="-3.5700000000000003"/>
  <obstacle x1="1.4699999999999995" y1="-3.63" x2="1.4099999999999995" y2="-3.5700000000000003"/>
  <obstacle x1="1.53" y1="-3.63" x2="1.47" y2="-3.5700000000000003"/>
  <obstacle x1="1.5899999999999996" y1="-3.63" x2="1.5299999999999996" y2="-3.5700000000000003"/>
  <obstacle x1="1.7699999999999994" y1="-3.63" x2="1.7099999999999993" y2="-3.5700000000000003"/>
  <obstacle x1="4.829999999999999" y1="-3.63" x2="4.769999999999999" y2="-3.5700000000000003"/>
  <obstacle x1="8.549999999999999" y1="-3.63" x2="8.49" y2="-3.5700000000000003"/>
  <obstacle x1="-5.91" y1="-3.69" x2="-5.970000000000001" y2="-3.6300000000000003"/>
  <obstacle x1="1.11" y1="-3.69" x2="1.05" y2="-3.6300000000000003"/>
  <obstacle x1="1.1699999999999997" y1="-3.69" x2="1.1099999999999997" y2="-3.6300000000000003"/>
  <obstacle x1="1.4699999999999995" y1="-3.69" x2="1.4099999999999995" y2="-3.6300000000000003"/>
  <obstacle x1="1.53" y1="-3.69" x2="1.47" y2="-3.6300000000000003"/>
  <obstacle x1="5.489999999999999" y1="-3.69" x2="5.429999999999999" y2="-3.6300000000000003"/>
  <obstacle x1="8.549999999999999" y1="-3.69" x2="8.49" y2="-3.6300000000000003"/>
  <obstacle x1="-5.91" y1="-3.75" x2="-5.970000000000001" y2="-3.6900000000000004"/>
  <obstacle x1="5.249999999999999" y1="-3.75" x2="5.189999999999999" y2="-3.6900000000000004"/>
  <obstacle x1="8.549999999999999" y1="-3.75" x2="8.49" y2="-3.6900000000000004"/>
  <obstacle x1="-5.91" y1="-3.81" x2="-5.970000000000001" y2="-3.7500000000000004"/>
  <obstacle x1="5.010000000000001" y1="-3.81" x2="4.95" y2="-3.7500000000000004"/>
  <obstacle x1="5.13" y1="-3.81" x2="5.069999999999999" y2="-3.7500000000000004"/>
  <obstacle x1="8.549999999999999" y1="-3.81" x2="8.49" y2="-3.7500000000000004"/>
  <obstacle x1="-5.91" y1="-3.8699999999999997" x2="-5.970000000000001" y2="-3.81"/>
  <obstacle x1="8.549999999999999" y1="-3.8699999999999997" x2="8.49" y2="-3.81"/>
  <obstacle x1="-5.91" y1="-3.9299999999999997" x2="-5.970000000000001" y2="-3.87"/>
  <obstacle x1="8.549999999999999" y1="-3.9299999999999997" x2="8.49" y2="-3.87"/>
  <obstacle x1="-5.91" y1="-3.9899999999999998" x2="-5.970000000000001" y2="-3.93"/>
  <obstacle x1="0.08999999999999961" y1="-3.9899999999999998" x2="0.02999999999999961" y2="-3.93"/>
  <obstacle x1="0.1500000000000001" y1="-3.9899999999999998" x2="0.09000000000000011" y2="-3.93"/>
  <obstacle x1="2.489999999999999" y1="-3.9899999999999998" x2="2.4299999999999993" y2="-3.93"/>
  <obstacle x1="2.5499999999999994" y1="-3.9899999999999998" x2="2.4899999999999998" y2="-3.93"/>
  <obstacle x1="8.549999999999999" y1="-3.9899999999999998" x2="8.49" y2="-3.93"/>
  <obstacle x1="-5.91" y1="-4.05" x2="-5.970000000000001" y2="-3.9899999999999998"/>
  <obstacle x1="5.13" y1="-4.05" x2="5.069999999999999" y2="-3.9899999999999998"/>
  <obstacle x1="8.549999999999999" y1="-4.05" x2="8.49" y2="-3.9899999999999998"/>
  <obstacle x1="-5.91" y1="-4.11" x2="-5.970000000000001" y2="-4.05"/>
  <obstacle x1="8.549999999999999" y1="-4.11" x2="8.49" y2="-4.05"/>
  <obstacle x1="-5.91" y1="-4.170000000000001" x2="-5.970000000000001" y2="-4.11"/>
  <obstacle x1="8.549999999999999" y1="-4.170000000000001" x2="8.49" y2="-4.11"/>
  <obstacle x1="-5.91" y1="-4.23" x2="-5.970000000000001" y2="-4.17"/>
  <obstacle x1="8.549999999999999" y1="-4.23" x2="8.49" y2="-4.17"/>
  <obstacle x1="-5.91" y1="-4.29" x2="-5.970000000000001" y2="-4.2299999999999995"/>
  <obstacle x1="8.549999999999999" y1="-4.29" x2="8.49" y2="-4.2299999999999995"/>
  <obstacle x1="-5.91" y1="-4.3500000000000005" x2="-5.970000000000001" y2="-4.29"/>
  <obstacle x1="8.549999999999999" y1="-4.3500000000000005" x2="8.49" y2="-4.29"/>
  <obstacle x1="-5.91" y1="-4.41" x2="-5.970000000000001" y2="-4.35"/>
  <obstacle x1="0.08999999999999961" y1="-4.41" x2="0.02999999999999961" y2="-4.35"/>
  <obstacle x1="0.1500000000000001" y1="-4.41" x2="0.09000000000000011" y2="-4.35"/>
  <obstacle x1="2.489999999999999" y1="-4.41" x2="2.4299999999999993" y2="-4.35"/>
  <obstacle x1="2.5499999999999994" y1="-4.41" x2="2.4899999999999998" y2="-4.35"/>
  <obstacle x1="8.549999999999999" y1="-4.41" x2="8.49" y2="-4.35"/>
  <obstacle x1="-5.91" y1="-4.47" x2="-5.970000000000001" y2="-4.409999999999999"/>
  <obstacle x1="8.549999999999999" y1="-4.47" x2="8.49" y2="-4.409999999999999"/>
  <obstacle x1="-5.91" y1="-4.53" x2="-5.970000000000001" y2="-4.47"/>
  <obstacle x1="8.549999999999999" y1="-4.53" x2="8.49" y2="-4.47"/>
  <obstacle x1="-5.91" y1="-4.590000000000001" x2="-5.970000000000001" y2="-4.53"/>
  <obstacle x1="8.549999999999999" y1="-4.590000000000001" x2="8.49" y2="-4.53"/>
  <obstacle x1="-5.91" y1="-4.65" x2="-5.970000000000001" y2="-4.59"/>
  <obstacle x1="8.549999999999999" y1="-4.65" x2="8.49" y2="-4.59"/>
  <obstacle x1="-5.91" y1="-4.71" x2="-5.970000000000001" y2="-4.6499999999999995"/>
  <obstacle x1="1.11" y1="-4.71" x2="1.05" y2="-4.6499999999999995"/>
  <obstacle x1="1.1699999999999997" y1="-4.71" x2="1.1099999999999997" y2="-4.6499999999999995"/>
  <obstacle x1="1.4699999999999995" y1="-4.71" x2="1.4099999999999995" y2="-4.6499999999999995"/>
  <obstacle x1="1.53" y1="-4.71" x2="1.47" y2="-4.6499999999999995"/>
  <obstacle x1="8.549999999999999" y1="-4.71" x2="8.49" y2="-4.6499999999999995"/>
  <obstacle x1="-5.91" y1="-4.7700000000000005" x2="-5.970000000000001" y2="-4.71"/>
  <obstacle x1="1.11" y1="-4.7700000000000005" x2="1.05" y2="-4.71"/>
  <obstacle x1="1.53" y1="-4.7700000000000005" x2="1.47" y2="-4.71"/>
  <obstacle x1="8.549999999999999" y1="-4.7700000000000005" x2="8.49" y2="-4.71"/>
  <obstacle x1="-5.91" y1="-4.83" x2="-5.970000000000001" y2="-4.77"/>
  <obstacle x1="8.549999999999999" y1="-4.83" x2="8.49" y2="-4.77"/>
  <obstacle x1="-5.91" y1="-4.890000000000001" x2="-5.970000000000001" y2="-4.83"/>
  <obstacle x1="8.549999999999999" y1="-4.890000000000001" x2="8.49" y2="-4.83"/>
  <obstacle x1="-5.91" y1="-4.95" x2="-5.970000000000001" y2="-4.89"/>
  <obstacle x1="8.549999999999999" y1="-4.95" x2="8.49" y2="-4.89"/>
  <obstacle x1="-5.91" y1="-5.010000000000001" x2="-5.970000000000001" y2="-4.95"/>
  <obstacle x1="-3.6900000000000004" y1="-5.010000000000001" x2="-3.75" y2="-4.95"/>
  <obstacle x1="8.549999999999999" y1="-5.010000000000001" x2="8.49" y2="-4.95"/>
  <obstacle x1="-5.91" y1="-5.07" x2="-5.970000000000001" y2="-5.01"/>
  <obstacle x1="8.549999999999999" y1="-5.07" x2="8.49" y2="-5.01"/>
  <obstacle x1="-5.91" y1="-5.13" x2="-5.970000000000001" y2="-5.069999999999999"/>
  <obstacle x1="8.549999999999999" y1="-5.13" x2="8.49" y2="-5.069999999999999"/>
  <obstacle x1="-5.91" y1="-5.19" x2="-5.970000000000001" y2="-5.13"/>
  <obstacle x1="8.549999999999999" y1="-5.19" x2="8.49" y2="-5.13"/>
  <obstacle x1="-5.91" y1="-5.25" x2="-5.970000000000001" y2="-5.1899999999999995"/>
  <obstacle x1="8.549999999999999" y1="-5.25" x2="8.49" y2="-5.1899999999999995"/>
  <obstacle x1="-5.91" y1="-5.3100000000000005" x2="-5.970000000000001" y2="-5.25"/>
  <obstacle x1="8.549999999999999" y1="-5.3100000000000005" x2="8.49" y2="-5.25"/>
  <obstacle x1="-5.91" y1="-5.37" x2="-5.970000000000001" y2="-5.31"/>
  <obstacle x1="8.549999999999999" y1="-5.37" x2="8.49" y2="-5.31"/>
  <obstacle x1="-5.91" y1="-5.430000000000001" x2="-5.970000000000001" y2="-5.37"/>
  <obstacle x1="8.549999999999999" y1="-5.430000000000001" x2="8.49" y2="-5.37"/>
  <obstacle x1="-5.91" y1="-5.49" x2="-5.970000000000001" y2="-5.43"/>
  <obstacle x1="8.549999999999999" y1="-5.49" x2="8.49" y2="-5.43"/>
  <obstacle x1="-5.91" y1="-5.55" x2="-5.970000000000001" y2="-5.489999999999999"/>
  <obstacle x1="8.549999999999999" y1="-5.55" x2="8.49" y2="-5.489999999999999"/>
  <obstacle x1="-5.91" y1="-5.61" x2="-5.970000000000001" y2="-5.55"/>
  <obstacle x1="8.549999999999999" y1="-5.61" x2="8.49" y2="-5.55"/>
  <obstacle x1="-5.91" y1="-5.67" x2="-5.970000000000001" y2="-5.609999999999999"/>
  <obstacle x1="8.549999999999999" y1="-5.67" x2="8.49" y2="-5.609999999999999"/>
  <obstacle x1="-5.91" y1="-5.73" x2="-5.970000000000001" y2="-5.67"/>
  <obstacle x1="8.549999999999999" y1="-5.73" x2="8.49" y2="-5.67"/>
  <obstacle x1="-5.91" y1="-5.79" x2="-5.970000000000001" y2="-5.7299999999999995"/>
  <obstacle x1="8.549999999999999" y1="-5.79" x2="8.49" y2="-5.7299999999999995"/>
  <obstacle x1="-5.91" y1="-5.8500000000000005" x2="-5.970000000000001" y2="-5.79"/>
  <obstacle x1="8.549999999999999" y1="-5.8500000000000005" x2="8.49" y2="-5.79"/>
  <obstacle x1="-5.91" y1="-5.91" x2="-5.970000000000001" y2="-5.85"/>
  <obstacle x1="-5.85" y1="-5.91" x2="-5.91" y2="-5.85"/>
  <obstacle x1="-5.79" y1="-5.91" x2="-5.8500000000000005" y2="-5.85"/>
  <obstacle x1="-5.7299999999999995" y1="-5.91" x2="-5.79" y2="-5.85"/>
  <obstacle x1="-5.67" y1="-5.91" x2="-5.73" y2="-5.85"/>
  <obstacle x1="-5.609999999999999" y1="-5.91" x2="-5.67" y2="-5.85"/>
  <obstacle x1="-5.55" y1="-5.91" x2="-5.61" y2="-5.85"/>
  <obstacle x1="-5.489999999999999" y1="-5.91" x2="-5.55" y2="-5.85"/>
  <obstacle x1="-5.43" y1="-5.91" x2="-5.49" y2="-5.85"/>
  <obstacle x1="-5.37" y1="-5.91" x2="-5.430000000000001" y2="-5.85"/>
  <obstacle x1="-5.31" y1="-5.91" x2="-5.37" y2="-5.85"/>
  <obstacle x1="-5.25" y1="-5.91" x2="-5.3100000000000005" y2="-5.85"/>
  <obstacle x1="-5.1899999999999995" y1="-5.91" x2="-5.25" y2="-5.85"/>
  <obstacle x1="-5.13" y1="-5.91" x2="-5.19" y2="-5.85"/>
  <obstacle x1="-5.069999999999999" y1="-5.91" x2="-5.13" y2="-5.85"/>
  <obstacle x1="-5.01" y1="-5.91" x2="-5.07" y2="-5.85"/>
  <obstacle x1="-4.95" y1="-5.91" x2="-5.010000000000001" y2="-5.85"/>
  <obstacle x1="-4.89" y1="-5.91" x2="-4.95" y2="-5.85"/>
  <obstacle x1="-4.83" y1="-5.91" x2="-4.890000000000001" y2="-5.85"/>
  <obstacle x1="-4.77" y1="-5.91" x2="-4.83" y2="-5.85"/>
  <obstacle x1="-4.71" y1="-5.91" x2="-4.7700000000000005" y2="-5.85"/>
  <obstacle x1="-4.6499999999999995" y1="-5.91" x2="-4.71" y2="-5.85"/>
  <obstacle x1="-4.59" y1="-5.91" x2="-4.65" y2="-5.85"/>
  <obstacle x1="-4.53" y1="-5.91" x2="-4.590000000000001" y2="-5.85"/>
  <obstacle x1="-4.47" y1="-5.91" x2="-4.53" y2="-5.85"/>
  <obstacle x1="-4.409999999999999" y1="-5.91" x2="-4.47" y2="-5.85"/>
  <obstacle x1="-4.35" y1="-5.91" x2="-4.41" y2="-5.85"/>
  <obstacle x1="-4.29" y1="-5.91" x2="-4.3500000000000005" y2="-5.85"/>
  <obstacle x1="-4.2299999999999995" y1="-5.91" x2="-4.29" y2="-5.85"/>
  <obstacle x1="-4.17" y1="-5.91" x2="-4.23" y2="-5.85"/>
  <obstacle x1="-4.11" y1="-5.91" x2="-4.170000000000001" y2="-5.85"/>
  <obstacle x1="-4.05" y1="-5.91" x2="-4.11" y2="-5.85"/>
  <obstacle x1="-3.9899999999999998" y1="-5.91" x2="-4.05" y2="-5.85"/>
  <obstacle x1="-3.93" y1="-5.91" x2="-3.9899999999999998" y2="-5.85"/>
  <obstacle x1="-3.87" y1="-5.91" x2="-3.9299999999999997" y2="-5.85"/>
  <obstacle x1="-3.81" y1="-5.91" x2="-3.8699999999999997" y2="-5.85"/>
  <obstacle x1="-3.7500000000000004" y1="-5.91" x2="-3.81" y2="-5.85"/>
  <obstacle x1="-3.6900000000000004" y1="-5.91" x2="-3.75" y2="-5.85"/>
  <obstacle x1="-3.6300000000000003" y1="-5.91" x2="-3.69" y2="-5.85"/>
  <obstacle x1="-3.5700000000000003" y1="-5.91" x2="-3.63" y2="-5.85"/>
  <obstacle x1="-3.5100000000000002" y1="-5.91" x2="-3.57" y2="-5.85"/>
  <obstacle x1="-3.45" y1="-5.91" x2="-3.51" y2="-5.85"/>
  <obstacle x1="-3.39" y1="-5.91" x2="-3.4499999999999997" y2="-5.85"/>
  <obstacle x1="-3.3300000000000005" y1="-5.91" x2="-3.39" y2="-5.85"/>
  <obstacle x1="-3.2700000000000005" y1="-5.91" x2="-3.33" y2="-5.85"/>
  <obstacle x1="-3.2100000000000004" y1="-5.91" x2="-3.27" y2="-5.85"/>
  <obstacle x1="-3.1500000000000004" y1="-5.91" x2="-3.21" y2="-5.85"/>
  <obstacle x1="-3.0900000000000003" y1="-5.91" x2="-3.15" y2="-5.85"/>
  <obstacle x1="-3.0300000000000002" y1="-5.91" x2="-3.09" y2="-5.85"/>
  <obstacle x1="-2.97" y1="-5.91" x2="-3.03" y2="-5.85"/>
  <obstacle x1="-2.91" y1="-5.91" x2="-2.9699999999999998" y2="-5.85"/>
  <obstacle x1="-2.85" y1="-5.91" x2="-2.9099999999999997" y2="-5.85"/>
  <obstacle x1="-2.7900000000000005" y1="-5.91" x2="-2.85" y2="-5.85"/>
  <obstacle x1="-2.7300000000000004" y1="-5.91" x2="-2.79" y2="-5.85"/>
  <obstacle x1="-2.6700000000000004" y1="-5.91" x2="-2.73" y2="-5.85"/>
  <obstacle x1="-2.6100000000000003" y1="-5.91" x2="-2.67" y2="-5.85"/>
  <obstacle x1="-2.5500000000000003" y1="-5.91" x2="-2.61" y2="-5.85"/>
  <obstacle x1="-2.49" y1="-5.91" x2="-2.55" y2="-5.85"/>
  <obstacle x1="-2.43" y1="-5.91" x2="-2.4899999999999998" y2="-5.85"/>
  <obstacle x1="-2.3700000000000006" y1="-5.91" x2="-2.43" y2="-5.85"/>
  <obstacle x1="-2.3100000000000005" y1="-5.91" x2="-2.37" y2="-5.85"/>
  <obstacle x1="-2.2500000000000004" y1="-5.91" x2="-2.31" y2="-5.85"/>
  <obstacle x1="-2.1900000000000004" y1="-5.91" x2="-2.25" y2="-5.85"/>
  <obstacle x1="-2.1300000000000003" y1="-5.91" x2="-2.19" y2="-5.85"/>
  <obstacle x1="-2.0700000000000003" y1="-5.91" x2="-2.13" y2="-5.85"/>
  <obstacle x1="-2.0100000000000002" y1="-5.91" x2="-2.07" y2="-5.85"/>
  <obstacle x1="-1.9500000000000004" y1="-5.91" x2="-2.0100000000000002" y2="-5.85"/>
  <obstacle x1="-1.89" y1="-5.91" x2="-1.95" y2="-5.85"/>
  <obstacle x1="-1.8300000000000003" y1="-5.91" x2="-1.8900000000000003" y2="-5.85"/>
  <obstacle x1="-1.7699999999999998" y1="-5.91" x2="-1.8299999999999998" y2="-5.85"/>
  <obstacle x1="-1.7100000000000002" y1="-5.91" x2="-1.7700000000000002" y2="-5.85"/>
  <obstacle x1="-1.6499999999999997" y1="-5.91" x2="-1.7099999999999997" y2="-5.85"/>
  <obstacle x1="-1.59" y1="-5.91" x2="-1.6500000000000001" y2="-5.85"/>
  <obstacle x1="-1.5300000000000005" y1="-5.91" x2="-1.5900000000000005" y2="-5.85"/>
  <obstacle x1="-1.47" y1="-5.91" x2="-1.53" y2="-5.85"/>
  <obstacle x1="-1.4100000000000004" y1="-5.91" x2="-1.4700000000000004" y2="-5.85"/>
  <obstacle x1="-1.3499999999999999" y1="-5.91" x2="-1.41" y2="-5.85"/>
  <obstacle x1="-1.2900000000000003" y1="-5.91" x2="-1.3500000000000003" y2="-5.85"/>
  <obstacle x1="-1.2299999999999998" y1="-5.91" x2="-1.2899999999999998" y2="-5.85"/>
  <obstacle x1="-1.1700000000000002" y1="-5.91" x2="-1.2300000000000002" y2="-5.85"/>
  <obstacle x1="-1.1100000000000005" y1="-5.91" x2="-1.1700000000000006" y2="-5.85"/>
  <obstacle x1="-1.05" y1="-5.91" x2="-1.11" y2="-5.85"/>
  <obstacle x1="-0.9900000000000004" y1="-5.91" x2="-1.0500000000000005" y2="-5.85"/>
  <obstacle x1="-0.9299999999999999" y1="-5.91" x2="-0.99" y2="-5.85"/>
  <obstacle x1="-0.8700000000000003" y1="-5.91" x2="-0.9300000000000004" y2="-5.85"/>
  <obstacle x1="-0.8099999999999998" y1="-5.91" x2="-0.8699999999999999" y2="-5.85"/>
  <obstacle x1="-0.7500000000000002" y1="-5.91" x2="-0.8100000000000003" y2="-5.85"/>
  <obstacle x1="-0.6900000000000006" y1="-5.91" x2="-0.7500000000000007" y2="-5.85"/>
  <obstacle x1="-0.6300000000000001" y1="-5.91" x2="-0.6900000000000002" y2="-5.85"/>
  <obstacle x1="-0.5700000000000005" y1="-5.91" x2="-0.6300000000000006" y2="-5.85"/>
  <obstacle x1="-0.51" y1="-5.91" x2="-0.5700000000000001" y2="-5.85"/>
  <obstacle x1="-0.4500000000000004" y1="-5.91" x2="-0.5100000000000005" y2="-5.85"/>
  <obstacle x1="-0.3899999999999999" y1="-5.91" x2="-0.44999999999999996" y2="-5.85"/>
  <obstacle x1="-0.3300000000000003" y1="-5.91" x2="-0.39000000000000035" y2="-5.85"/>
  <obstacle x1="-0.2699999999999998" y1="-5.91" x2="-0.32999999999999985" y2="-5.85"/>
  <obstacle x1="-0.21000000000000021" y1="-5.91" x2="-0.27000000000000024" y2="-5.85"/>
  <obstacle x1="-0.1500000000000006" y1="-5.91" x2="-0.2100000000000006" y2="-5.85"/>
  <obstacle x1="-0.09000000000000011" y1="-5.91" x2="-0.1500000000000001" y2="-5.85"/>
  <obstacle x1="-0.0300000000000005" y1="-5.91" x2="-0.0900000000000005" y2="-5.85"/>
  <obstacle x1="0.03" y1="-5.91" x2="-0.03" y2="-5.85"/>
  <obstacle x1="0.08999999999999961" y1="-5.91" x2="0.02999999999999961" y2="-5.85"/>
  <obstacle x1="0.1500000000000001" y1="-5.91" x2="0.09000000000000011" y2="-5.85"/>
  <obstacle x1="0.20999999999999971" y1="-5.91" x2="0.14999999999999972" y2="-5.85"/>
  <obstacle x1="0.27000000000000024" y1="-5.91" x2="0.21000000000000021" y2="-5.85"/>
  <obstacle x1="0.32999999999999985" y1="-5.91" x2="0.2699999999999998" y2="-5.85"/>
  <obstacle x1="0.38999999999999946" y1="-5.91" x2="0.3299999999999994" y2="-5.85"/>
  <obstacle x1="0.44999999999999996" y1="-5.91" x2="0.3899999999999999" y2="-5.85"/>
  <obstacle x1="0.5099999999999996" y1="-5.91" x2="0.4499999999999995" y2="-5.85"/>
  <obstacle x1="0.5700000000000001" y1="-5.91" x2="0.51" y2="-5.85"/>
  <obstacle x1="0.6299999999999997" y1="-5.91" x2="0.5699999999999996" y2="-5.85"/>
  <obstacle x1="0.6900000000000002" y1="-5.91" x2="0.6300000000000001" y2="-5.85"/>
  <obstacle x1="0.7499999999999998" y1="-5.91" x2="0.6899999999999997" y2="-5.85"/>
  <obstacle x1="0.8099999999999994" y1="-5.91" x2="0.7499999999999993" y2="-5.85"/>
  <obstacle x1="0.8699999999999999" y1="-5.91" x2="0.8099999999999998" y2="-5.85"/>
  <obstacle x1="0.9299999999999995" y1="-5.91" x2="0.8699999999999994" y2="-5.85"/>
  <obstacle x1="0.99" y1="-5.91" x2="0.9299999999999999" y2="-5.85"/>
  <obstacle x1="1.0499999999999996" y1="-5.91" x2="0.9899999999999995" y2="-5.85"/>
  <obstacle x1="1.11" y1="-5.91" x2="1.05" y2="-5.85"/>
  <obstacle x1="1.1699999999999997" y1="-5.91" x2="1.1099999999999997" y2="-5.85"/>
  <obstacle x1="1.2299999999999993" y1="-5.91" x2="1.1699999999999993" y2="-5.85"/>
  <obstacle x1="1.2899999999999998" y1="-5.91" x2="1.2299999999999998" y2="-5.85"/>
  <obstacle x1="1.3499999999999994" y1="-5.91" x2="1.2899999999999994" y2="-5.85"/>
  <obstacle x1="1.41" y1="-5.91" x2="1.3499999999999999" y2="-5.85"/>
  <obstacle x1="1.4699999999999995" y1="-5.91" x2="1.4099999999999995" y2="-5.85"/>
  <obstacle x1="1.53" y1="-5.91" x2="1.47" y2="-5.85"/>
  <obstacle x1="1.5899999999999996" y1="-5.91" x2="1.5299999999999996" y2="-5.85"/>
  <obstacle x1="1.6500000000000001" y1="-5.91" x2="1.59" y2="-5.85"/>
  <obstacle x1="1.7099999999999997" y1="-5.91" x2="1.6499999999999997" y2="-5.85"/>
  <obstacle x1="1.7699999999999994" y1="-5.91" x2="1.7099999999999993" y2="-5.85"/>
  <obstacle x1="1.8299999999999998" y1="-5.91" x2="1.7699999999999998" y2="-5.85"/>
  <obstacle x1="1.8899999999999995" y1="-5.91" x2="1.8299999999999994" y2="-5.85"/>
  <obstacle x1="1.95" y1="-5.91" x2="1.89" y2="-5.85"/>
  <obstacle x1="2.0099999999999993" y1="-5.91" x2="1.9499999999999995" y2="-5.85"/>
  <obstacle x1="2.069999999999999" y1="-5.91" x2="2.0099999999999993" y2="-5.85"/>
  <obstacle x1="2.1299999999999994" y1="-5.91" x2="2.07" y2="-5.85"/>
  <obstacle x1="2.19" y1="-5.91" x2="2.1300000000000003" y2="-5.85"/>
  <obstacle x1="2.2499999999999987" y1="-5.91" x2="2.189999999999999" y2="-5.85"/>
  <obstacle x1="2.309999999999999" y1="-5.91" x2="2.2499999999999996" y2="-5.85"/>
  <obstacle x1="2.3699999999999997" y1="-5.91" x2="2.31" y2="-5.85"/>
  <obstacle x1="2.43" y1="-5.91" x2="2.3700000000000006" y2="-5.85"/>
  <obstacle x1="2.489999999999999" y1="-5.91" x2="2.4299999999999993" y2="-5.85"/>
  <obstacle x1="2.5499999999999994" y1="-5.91" x2="2.4899999999999998" y2="-5.85"/>
  <obstacle x1="2.61" y1="-5.91" x2="2.5500000000000003" y2="-5.85"/>
  <obstacle x1="2.6700000000000004" y1="-5.91" x2="2.6100000000000008" y2="-5.85"/>
  <obstacle x1="2.729999999999999" y1="-5.91" x2="2.6699999999999995" y2="-5.85"/>
  <obstacle x1="2.7899999999999996" y1="-5.91" x2="2.73" y2="-5.85"/>
  <obstacle x1="2.85" y1="-5.91" x2="2.7900000000000005" y2="-5.85"/>
  <obstacle x1="2.909999999999999" y1="-5.91" x2="2.849999999999999" y2="-5.85"/>
  <obstacle x1="2.9699999999999993" y1="-5.91" x2="2.9099999999999997" y2="-5.85"/>
  <obstacle x1="3.03" y1="-5.91" x2="2.97" y2="-5.85"/>
  <obstacle x1="3.0900000000000003" y1="-5.91" x2="3.0300000000000007" y2="-5.85"/>
  <obstacle x1="3.149999999999999" y1="-5.91" x2="3.0899999999999994" y2="-5.85"/>
  <obstacle x1="3.2099999999999995" y1="-5.91" x2="3.15" y2="-5.85"/>
  <obstacle x1="3.27" y1="-5.91" x2="3.2100000000000004" y2="-5.85"/>
  <obstacle x1="3.3299999999999987" y1="-5.91" x2="3.269999999999999" y2="-5.85"/>
  <obstacle x1="3.3899999999999992" y1="-5.91" x2="3.3299999999999996" y2="-5.85"/>
  <obstacle x1="3.4499999999999997" y1="-5.91" x2="3.39" y2="-5.85"/>
  <obstacle x1="3.5100000000000002" y1="-5.91" x2="3.4500000000000006" y2="-5.85"/>
  <obstacle x1="3.569999999999999" y1="-5.91" x2="3.5099999999999993" y2="-5.85"/>
  <obstacle x1="3.6299999999999994" y1="-5.91" x2="3.57" y2="-5.85"/>
  <obstacle x1="3.69" y1="-5.91" x2="3.6300000000000003" y2="-5.85"/>
  <obstacle x1="3.7499999999999987" y1="-5.91" x2="3.689999999999999" y2="-5.85"/>
  <obstacle x1="3.809999999999999" y1="-5.91" x2="3.7499999999999996" y2="-5.85"/>
  <obstacle x1="3.8699999999999997" y1="-5.91" x2="3.81" y2="-5.85"/>
  <obstacle x1="3.93" y1="-5.91" x2="3.8700000000000006" y2="-5.85"/>
  <obstacle x1="3.989999999999999" y1="-5.91" x2="3.9299999999999993" y2="-5.85"/>
  <obstacle x1="4.05" y1="-5.91" x2="3.9899999999999998" y2="-5.85"/>
  <obstacle x1="4.11" y1="-5.91" x2="4.05" y2="-5.85"/>
  <obstacle x1="4.169999999999999" y1="-5.91" x2="4.1099999999999985" y2="-5.85"/>
  <obstacle x1="4.2299999999999995" y1="-5.91" x2="4.169999999999999" y2="-5.85"/>
  <obstacle x1="4.29" y1="-5.91" x2="4.2299999999999995" y2="-5.85"/>
  <obstacle x1="4.3500000000000005" y1="-5.91" x2="4.29" y2="-5.85"/>
  <obstacle x1="4.409999999999999" y1="-5.91" x2="4.349999999999999" y2="-5.85"/>
  <obstacle x1="4.47" y1="-5.91" x2="4.409999999999999" y2="-5.85"/>
  <obstacle x1="4.53" y1="-5.91" x2="4.47" y2="-5.85"/>
  <obstacle x1="4.589999999999999" y1="-5.91" x2="4.5299999999999985" y2="-5.85"/>
  <obstacle x1="4.6499999999999995" y1="-5.91" x2="4.589999999999999" y2="-5.85"/>
  <obstacle x1="4.71" y1="-5.91" x2="4.6499999999999995" y2="-5.85"/>
  <obstacle x1="4.7700000000000005" y1="-5.91" x2="4.71" y2="-5.85"/>
  <obstacle x1="4.829999999999999" y1="-5.91" x2="4.769999999999999" y2="-5.85"/>
  <obstacle x1="4.89" y1="-5.91" x2="4.829999999999999" y2="-5.85"/>
  <obstacle x1="4.95" y1="-5.91" x2="4.89" y2="-5.85"/>
  <obstacle x1="5.010000000000001" y1="-5.91" x2="4.95" y2="-5.85"/>
  <obstacle x1="5.069999999999999" y1="-5.91" x2="5.009999999999999" y2="-5.85"/>
  <obstacle x1="5.13" y1="-5.91" x2="5.069999999999999" y2="-5.85"/>
  <obstacle x1="5.19" y1="-5.91" x2="5.13" y2="-5.85"/>
  <obstacle x1="5.249999999999999" y1="-5.91" x2="5.189999999999999" y2="-5.85"/>
  <obstacle x1="5.31" y1="-5.91" x2="5.249999999999999" y2="-5.85"/>
  <obstacle x1="5.37" y1="-5.91" x2="5.31" y2="-5.85"/>
  <obstacle x1="5.430000000000001" y1="-5.91" x2="5.37" y2="-5.85"/>
  <obstacle x1="5.489999999999999" y1="-5.91" x2="5.429999999999999" y2="-5.85"/>
  <obstacle x1="5.55" y1="-5.91" x2="5.489999999999999" y2="-5.85"/>
  <obstacle x1="5.61" y1="-5.91" x2="5.55" y2="-5.85"/>
  <obstacle x1="5.669999999999999" y1="-5.91" x2="5.6099999999999985" y2="-5.85"/>
  <obstacle x1="5.7299999999999995" y1="-5.91" x2="5.669999999999999" y2="-5.85"/>
  <obstacle x1="5.79" y1="-5.91" x2="5.7299999999999995" y2="-5.85"/>
  <obstacle x1="5.8500000000000005" y1="-5.91" x2="5.79" y2="-5.85"/>
  <obstacle x1="5.909999999999999" y1="-5.91" x2="5.849999999999999" y2="-5.85"/>
  <obstacle x1="5.97" y1="-5.91" x2="5.909999999999999" y2="-5.85"/>
  <obstacle x1="6.03" y1="-5.91" x2="5.97" y2="-5.85"/>
  <obstacle x1="6.089999999999999" y1="-5.91" x2="6.0299999999999985" y2="-5.85"/>
  <obstacle x1="6.1499999999999995" y1="-5.91" x2="6.089999999999999" y2="-5.85"/>
  <obstacle x1="6.21" y1="-5.91" x2="6.1499999999999995" y2="-5.85"/>
  <obstacle x1="6.2700000000000005" y1="-5.91" x2="6.21" y2="-5.85"/>
  <obstacle x1="6.329999999999999" y1="-5.91" x2="6.269999999999999" y2="-5.85"/>
  <obstacle x1="6.39" y1="-5.91" x2="6.329999999999999" y2="-5.85"/>
  <obstacle x1="6.45" y1="-5.91" x2="6.39" y2="-5.85"/>
  <obstacle x1="6.510000000000001" y1="-5.91" x2="6.45" y2="-5.85"/>
  <obstacle x1="6.569999999999999" y1="-5.91" x2="6.509999999999999" y2="-5.85"/>
  <obstacle x1="6.63" y1="-5.91" x2="6.569999999999999" y2="-5.85"/>
  <obstacle x1="6.69" y1="-5.91" x2="6.63" y2="-5.85"/>
  <obstacle x1="6.749999999999999" y1="-5.91" x2="6.689999999999999" y2="-5.85"/>
  <obstacle x1="6.81" y1="-5.91" x2="6.749999999999999" y2="-5.85"/>
  <obstacle x1="6.87" y1="-5.91" x2="6.81" y2="-5.85"/>
  <obstacle x1="6.930000000000001" y1="-5.91" x2="6.87" y2="-5.85"/>
  <obstacle x1="6.989999999999999" y1="-5.91" x2="6.929999999999999" y2="-5.85"/>
  <obstacle x1="7.05" y1="-5.91" x2="6.989999999999999" y2="-5.85"/>
  <obstacle x1="7.11" y1="-5.91" x2="7.05" y2="-5.85"/>
  <obstacle x1="7.169999999999999" y1="-5.91" x2="7.1099999999999985" y2="-5.85"/>
  <obstacle x1="7.2299999999999995" y1="-5.91" x2="7.169999999999999" y2="-5.85"/>
  <obstacle x1="7.29" y1="-5.91" x2="7.2299999999999995" y2="-5.85"/>
  <obstacle x1="7.3500000000000005" y1="-5.91" x2="7.29" y2="-5.85"/>
  <obstacle x1="7.409999999999999" y1="-5.91" x2="7.349999999999999" y2="-5.85"/>
  <obstacle x1="7.47" y1="-5.91" x2="7.409999999999999" y2="-5.85"/>
  <obstacle x1="7.53" y1="-5.91" x2="7.47" y2="-5.85"/>
  <obstacle x1="7.589999999999999" y1="-5.91" x2="7.5299999999999985" y2="-5.85"/>
  <obstacle x1="7.6499999999999995" y1="-5.91" x2="7.589999999999999" y2="-5.85"/>
  <obstacle x1="7.71" y1="-5.91" x2="7.6499999999999995" y2="-5.85"/>
  <obstacle x1="7.7700000000000005" y1="-5.91" x2="7.71" y2="-5.85"/>
  <obstacle x1="7.829999999999999" y1="-5.91" x2="7.769999999999999" y2="-5.85"/>
  <obstacle x1="7.89" y1="-5.91" x2="7.829999999999999" y2="-5.85"/>
  <obstacle x1="7.95" y1="-5.91" x2="7.89" y2="-5.85"/>
  <obstacle x1="8.009999999999998" y1="-5.91" x2="7.949999999999998" y2="-5.85"/>
  <obstacle x1="8.069999999999999" y1="-5.91" x2="8.01" y2="-5.85"/>
  <obstacle x1="8.129999999999999" y1="-5.91" x2="8.07" y2="-5.85"/>
  <obstacle x1="8.19" y1="-5.91" x2="8.13" y2="-5.85"/>
  <obstacle x1="8.249999999999998" y1="-5.91" x2="8.19" y2="-5.85"/>
  <obstacle x1="8.309999999999999" y1="-5.91" x2="8.25" y2="-5.85"/>
  <obstacle x1="8.37" y1="-5.91" x2="8.31" y2="-5.85"/>
  <obstacle x1="8.429999999999998" y1="-5.91" x2="8.37" y2="-5.85"/>
  <obstacle x1="8.489999999999998" y1="-5.91" x2="8.43" y2="-5.85"/>
  <obstacle x1="8.549999999999999" y1="-5.91" x2="8.49" y2="-5.85"/>
</scenario>
